Workbook

Sheet Production
A1: Facility | B1: Production Size (gallons) | C1: Type | D1: Source
A2: Twelve's Moses Lake facility | B2: 50000 | C2: E-Jet SAF | D2: https://trellis.net/article/alaska-airlines-microsoft-twelve-sustainable-aviation-fuel/

Sheet Targets
A1: Country | B1: Year | C1: Type | D1: Size (Blend) | E1: Size (Gallons) | F1: Actual
A2: UK | B2: 2025 | C2: Blend | D2: 0.02 | E2: na
A3: UK | B3: 2030 | C3: Blend | D3: 0.1 | E3: na
A4: UK | B4: 2040 | C4: Blend | D4: 0.22 | E4: na
A5: UK | B5: 2050 | C5: Blend | D5: Net Zero | E5: na
A6: EU | B6: 2025 | C6: Blend | D6: 0.02 | E6: na
A7: EU | B7: 2030 | C7: Blend | D7: 0.06 | E7: na
A8: EU | B8: 2040 | C8: Blend | D8: 0.34 | E8: na
A9: EU | B9: 2050 | C9: Blend | D9: 0.7 | E9: na
A10: US | B10: 2030 | C10: Production | D10: na | E10: 3
A11: US | B11: 2050 | C11: Production | D11: na | E11: 35
A12: US | B12: 2024 | C12: Production | D12: na | E12: 0.039
A13: US | B13: 2030 | C13: Optimistic Production | E13: 2.1

Sheet Alaska Report
A1: Year | B1: ASMs | C1: RPMs | D1: Passengers | E1: Fuel gallons | F1: ASMs/gal | G1: Economic fuel $/gal | H1: RASM | I1: PRASM | J1: CASMex | K1: Operating Revenue | L1: Fuel expense | M1: Adjusted Pretax margin
A2: 2024 PF | B2: 91208000000 | C2: 76566000000 | D2: 57134000 | E2: 1123000000 | F2: 81.2 | G2: 2.74 | H2: 0.1511 | I2: 0.1371 | J2: 0.1091 | K2: 13779000000 | L2: 3075000000 | M2: 0.071
A3: 2025 | B3: 92962000000 | C3: 77110000000 | D3: 58627000 | E3: 1146000000 | F3: 81.1 | G3: 2.52 | H3: 0.1532 | I3: 0.1381 | J3: 0.1142 | K3: 14239000000 | L3: 2883000000 | M3: 0.028
A5: YoY Growth | B5: =(B3-B2)/B2 -> 0.019230769 | C5: =(C3-C2)/C2 -> 0.0071049813 | D5: =(D3-D2)/D2 -> 0.02613155 | E5: =(E3-E2)/E2 -> 0.020480855 | F5: =(F3-F2)/F2 -> -0.0012315271 | G5: =(G3-G2)/G2 -> -0.080291971 | H5: =(H3-H2)/H2 -> 0.013898081 | I5: =(I3-I2)/I2 -> 0.007293946 | ... M5: =(M3-M2)/M2 -> -0.6056338

Sheet Alaska Base
A1: Metric | B1: Year | C1: Value | D1: Units | E1: Source
A2: 2019 GHG Intensity Baseline | B2: 2019 | C2: 1.39 | D2: metric tons CO₂e / 1,000 RTM | E2: Sustain Report | G2: Derived metric | H2: Value
A3: 2025 GHG Intensity | B3: 2025 | C3: 1.33 | D3: metric tons CO2e / 1,000 RTM | E3: 2025 Impact Report | G3: Environmental_Total_Fuel | H3: =C4+C5 -> 1090676144
A4: 2025 Conventional Jet Fuel | B4: 2025 | C4: 1079785000 | D4: gallons | E4: 2025 Impact Report | G4: Environmental_SAF_Share | H4: =C20 -> 0.009985681
A5: 2025 SAF | B5: 2025 | C5: 10891144 | D5: gallons | E5: 2025 Impact Report | G5: Operating_SAF_Share | H5: =C19 -> 0.0095036161
A6: 2025 Operating Aircraft Fuel | B6: 2025 | C6: 1146000000 | D6: gallons | E6: 2025 10-K / operating statistics | G6: Observed_ASM_Growth | H6: =C11/C10-1 -> 0.019230769
A7: 2025 Into-plane Fuel Price | B7: 2025 | C7: 2.51 | D7: $/gallon | E7: 2025 10-K
A8: 2025 Total Operating Revenue | B8: 2025 | C8: 14239000000 | D8: $ | E8: 2025 10-K
A9: 2025 Passenger Revenue | B9: 2025 | C9: 12835000000 | D9: $ | E9: 2025 10-K
A10: 2024 PF ASM | B10: 2024 | C10: 91208000000 | D10: ASM | E10: 2025 10-K pro forma
A11: 2025 ASM | B11: 2025 | C11: 92962000000 | D11: ASM | E11: 2025 10-K
A12: 2025 Aircraft Scope 1 emissions | B12: 2025 | C12: 10428326 | D12: tCO2e | E12: 2025 Impact Report
A13: 2025 Vehicle Scope 1 emissions | B13: 2025 | C13: 13789 | D13: tCO2e | E13: 2025 Impact Report
A14: 2025 Facility heating Scope 1 emissions | B14: 2025 | C14: 6385 | D14: tCO2e | E14: 2025 Impact Report
A15: 2025 SAF N2O Scope 1 emissions | B15: 2025 | C15: 866 | D15: tCO2e | E15: 2025 Impact Report
A16: 2025 Scope 2 market-based emissions | B16: 2025 | C16: 13321 | D16: tCO2e | E16: 2025 Impact Report
A17: 2025 Scope 1 total | B17: 2025 | C17: 10449366 | D17: tCO2e | E17: 2025 Impact Report
A18: 2025 implied RTM | B18: 2025 | C18: =C12/C3*1000 -> 7.8408466e+09 | D18: RTM | E18: Derived: aircraft Scope 1 / GHG intensity × 1,000
A19: 2025 operating SAF share | B19: 2025 | C19: =C5/C6 -> 0.0095036161 | D19: % of operating fuel | E19: Derived: SAF gallons / operating aircraft fuel
A20: 2025 environmental-reporting SAF share | B20: 2025 | C20: =C5/(C4+C5) -> 0.009985681 | D20: % of env. fuel | E20: Derived: SAF / (conventional + SAF)
A21: 2025 Scope 3 total (context only) | B21: 2025 | C21: 3829342 | D21: tCO2e | E21: 2025 Impact Report; excluded from v1 operational net-zero model
A22: 2025 Cash & Cash Equivalents | B22: 2025 | C22: 627000000 | D22: $ | E22: 2025 10-K
A23: 2025 Marketable Securities | B23: 2025 | C23: 1496000000 | D23: $ | E23: 2025 10-K
A24: 2025 Cash + Marketable Securities | B24: 2025 | C24: =C22+C23 -> 2123000000 | D24: $ | E24: Derived
A25: 2025 Available Liquidity | B25: 2025 | C25: 2973000000 | D25: $ | E25: 2025 10-K; includes unused line of credit
A26: 2025 Operating Cash Flow | B26: 2025 | C26: 1200000000 | D26: $ | E26: 2025 10-K
A27: 2025 Capital Expenditures | B27: 2025 | C27: 1600000000 | D27: $ | E27: 2025 10-K
A28: 2026 Planned Capital Expenditures — midpoint | B28: 2026 | C28: 1450000000 | D28: $ | E28: 2026 Q1 10-Q guidance $1.4B–$1.5B
A29: 2031–2035 Aggregate Aircraft Commitments | B29: 2031 | C29: 4264000000 | D29: $ | E29: 2026 Q2 10-Q; 'thereafter' after 2030

Sheet EIA_AEO
A1: Year | B1: Fuel Cost (1987 dollars per MMBtu) | C1: Fuel Price Index: | D1: Aircraft Efficiency: Average Aircraft | E1: Efficiency Index | F1: Commercial Jet Fuel (US): Fuel Consumption (trillion Btu)
A2: 2025 | B2: 6.6966219 | C2: =B2/ _xlfn.XLOOKUP(2025,$A$2:$A$27,$B$2:$B$27) -> 1 | D2: 85.781158 | E2: =D2/ _xlfn.XLOOKUP(2025,$A$2:$A$27,$D$2:$D$27) -> 1 | F2: 3230.0942
A3: 2026 | B3: 5.9723396 | C3: =B3/ _xlfn.XLOOKUP(2025,$A$2:$A$27,$B$2:$B$27) -> 0.89184364 | D3: 86.455696 | E3: =D3/ _xlfn.XLOOKUP(2025,$A$2:$A$27,$D$2:$D$27) -> 1.0078635 | F3: 3275.9133
A4: 2027 | B4: 6.4054852 | C4: =B4/ _xlfn.XLOOKUP(2025,$A$2:$A$27,$B$2:$B$27) -> 0.95652484 | D4: 87.136665 | E4: =D4/ _xlfn.XLOOKUP(2025,$A$2:$A$27,$D$2:$D$27) -> 1.0158019 | F4: 3303.1797
A5: 2028 | B5: 6.5878377 | C5: =B5/ _xlfn.XLOOKUP(2025,$A$2:$A$27,$B$2:$B$27) -> 0.98375536 | D5: 87.83371 | E5: =D5/ _xlfn.XLOOKUP(2025,$A$2:$A$27,$D$2:$D$27) -> 1.0239278 | F5: 3304.9766
A6: 2029 | B6: 6.7469621 | C6: =B6/ _xlfn.XLOOKUP(2025,$A$2:$A$27,$B$2:$B$27) -> 1.0075172 | D6: 88.507492 | E6: =D6/ _xlfn.XLOOKUP(2025,$A$2:$A$27,$D$2:$D$27) -> 1.0317824 | F6: 3320.0674
A7: 2030 | B7: 6.7818222 | C7: =B7/ _xlfn.XLOOKUP(2025,$A$2:$A$27,$B$2:$B$27) -> 1.0127229 | D7: 89.191437 | E7: =D7/ _xlfn.XLOOKUP(2025,$A$2:$A$27,$D$2:$D$27) -> 1.0397556 | F7: 3347.7463
A8: 2031 | B8: 6.7284436 | C8: =B8/ _xlfn.XLOOKUP(2025,$A$2:$A$27,$B$2:$B$27) -> 1.0047519 | D8: 89.892052 | E8: =D8/ _xlfn.XLOOKUP(2025,$A$2:$A$27,$D$2:$D$27) -> 1.047923 | F8: 3372.7368
A9: 2032 | B9: 6.7404766 | C9: =B9/ _xlfn.XLOOKUP(2025,$A$2:$A$27,$B$2:$B$27) -> 1.0065488 | D9: 90.644325 | E9: =D9/ _xlfn.XLOOKUP(2025,$A$2:$A$27,$D$2:$D$27) -> 1.0566927 | F9: 3400.6318
A10: 2033 | B10: 6.9223495 | C10: =B10/ _xlfn.XLOOKUP(2025,$A$2:$A$27,$B$2:$B$27) -> 1.0337077 | D10: 91.404976 | E10: =D10/ _xlfn.XLOOKUP(2025,$A$2:$A$27,$D$2:$D$27) -> 1.0655601 | F10: 3436.5942
A11: 2034 | B11: 7.1716175 | C11: =B11/ _xlfn.XLOOKUP(2025,$A$2:$A$27,$B$2:$B$27) -> 1.0709306 | D11: 92.163483 | E11: =D11/ _xlfn.XLOOKUP(2025,$A$2:$A$27,$D$2:$D$27) -> 1.0744024 | F11: 3481.7234
A12: 2035 | B12: 7.2526112 | C12: =B12/ _xlfn.XLOOKUP(2025,$A$2:$A$27,$B$2:$B$27) -> 1.0830253 | D12: 92.923798 | E12: =D12/ _xlfn.XLOOKUP(2025,$A$2:$A$27,$D$2:$D$27) -> 1.0832658 | F12: 3531.4907
A13: 2036 | B13: 7.3257723 | C13: =B13/ _xlfn.XLOOKUP(2025,$A$2:$A$27,$B$2:$B$27) -> 1.0939504 | D13: 93.685272 | E13: =D13/ _xlfn.XLOOKUP(2025,$A$2:$A$27,$D$2:$D$27) -> 1.0921428 | F13: 3570.2549
... A27: 2050 | B27: 9.1152992 | C27: =B27/ _xlfn.XLOOKUP(2025,$A$2:$A$27,$B$2:$B$27) -> 1.3611787 | D27: 105.05097 | E27: =D27/ _xlfn.XLOOKUP(2025,$A$2:$A$27,$D$2:$D$27) -> 1.2246392 | F27: 4013.6313
A29: EIA 2025–2035 efficiency CAGR | B29: =(_xlfn.XLOOKUP(2035,$A$2:$A$27,$D$2:$D$27)/ _xlfn.XLOOKUP(2025,$A$2:$A$27,$D$2:$D$27))^(1/10)-1 -> 0.008030109

Sheet EPA_SAF
A1: RIN Year | B1: Month | C1: Producer Type | D1: Fuel (D Code) | E1: Fuel Category | F1: RINs | G1: Volume (Gal.) | H1: SAF_Flag | I1: Period
A2: 2018 | B2: 1 | C2: Domestic | D2: D3 | E2: Cellulosic Ethanol (EV 1.0) | F2: 760163 | G2: 760163 | H2: =--ISNUMBER(SEARCH("Jet Fuel",E2)) -> 0 | I2: =DATE(A2,B2,1) -> 43101
A3: 2018 | B3: 1 | C3: Domestic | D3: D3 | E3: Renewable Liquefied Natural Gas | F3: 186414 | G3: 186414 | H3: =--ISNUMBER(SEARCH("Jet Fuel",E3)) -> 0 | I3: =DATE(A3,B3,1) -> 43101
A4: 2018 | B4: 1 | C4: Domestic | D4: D3 | E4: Renewable Compressed Natural Gas | F4: 20688 | G4: 20688 | H4: =--ISNUMBER(SEARCH("Jet Fuel",E4)) -> 0 | I4: =DATE(A4,B4,1) -> 43101
A5: 2018 | B5: 1 | C5: Domestic | D5: D4 | E5: Biodiesel (EV 1.5) | F5: 165745904 | G5: 110496056 | H5: =--ISNUMBER(SEARCH("Jet Fuel",E5)) -> 0 | I5: =DATE(A5,B5,1) -> 43101
A6: 2018 | B6: 1 | C6: Foreign Generation | D6: D4 | E6: Non-ester Renewable Diesel (EV 1.7) | F6: 26685400 | G6: 15697294 | H6: =--ISNUMBER(SEARCH("Jet Fuel",E6)) -> 0 | I6: =DATE(A6,B6,1) -> 43101
A7: 2018 | B7: 1 | C7: Domestic | D7: D4 | E7: Non-ester Renewable Diesel (EV 1.7) | F7: 22710110 | G7: 13358879 | H7: =--ISNUMBER(SEARCH("Jet Fuel",E7)) -> 0 | I7: =DATE(A7,B7,1) -> 43101
A8: 2018 | B8: 1 | C8: Importer | D8: D4 | E8: Biodiesel (EV 1.5) | F8: 16044167 | G8: 10696089 | H8: =--ISNUMBER(SEARCH("Jet Fuel",E8)) -> 0 | I8: =DATE(A8,B8,1) -> 43101
A9: 2018 | B9: 1 | C9: Domestic | D9: D4 | E9: Renewable Jet Fuel (EV 1.6) | F9: 223543 | G9: 139714 | H9: =--ISNUMBER(SEARCH("Jet Fuel",E9)) -> 1 | I9: =DATE(A9,B9,1) -> 43101
A10: 2018 | B10: 1 | C10: Domestic | D10: D5 | E10: Renewable Naphtha (EV 1.5) | F10: 2631674 | G10: 1754449 | H10: =--ISNUMBER(SEARCH("Jet Fuel",E10)) -> 0 | I10: =DATE(A10,B10,1) -> 43101
A11: 2018 | B11: 1 | C11: Domestic | D11: D5 | E11: Non-cellulosic Ethanol (EV 1.0) | F11: 2191637 | G11: 2191637 | H11: =--ISNUMBER(SEARCH("Jet Fuel",E11)) -> 0 | I11: =DATE(A11,B11,1) -> 43101
A12: 2018 | B12: 1 | C12: Domestic | D12: D5 | E12: Non-ester Renewable Diesel (EV 1.7) | F12: 547014 | G12: 321773 | H12: =--ISNUMBER(SEARCH("Jet Fuel",E12)) -> 0 | I12: =DATE(A12,B12,1) -> 43101
A13: 2018 | B13: 1 | C13: Domestic | D13: D5 | E13: Renewable Heating Oil (EV 1.6) | F13: 422563 | G13: 264103 | H13: =--ISNUMBER(SEARCH("Jet Fuel",E13)) -> 0 | I13: =DATE(A13,B13,1) -> 43101
... A2160: 2026 | B2160: 7 | C2160: Importer | D2160: D6 | E2160: Non-cellulosic Ethanol (EV 1.0) | F2160: 1514114 | G2160: 1514114 | H2160: =--ISNUMBER(SEARCH("Jet Fuel",E2160)) -> 0 | I2160: =DATE(A2160,B2160,1) -> 46204

Sheet EPA_SAF_PIV
A1: SAF_Flag | H1: SAF_Flag
H2: Month
B3: Domestic | C3: Foreign Generation | D3: Importer | E3: Grand Total
A4: Row Labels | E4: Grand Total | I4: Domestic | J4: Foreign Generation | K4: Importer | L4: Grand Total
A5: 2018 | B5: 17441884577 | C5: 309846637 | D5: 305428514 | E5: 18057159728 | H5: Row Labels | L5: Grand Total
A6: 2019 | B6: 17354299933 | C6: 420373097 | D6: 434991489 | E6: 18209664519 | I6: 158951615015 | J6: 3050392200 | K6: 3305813393 | L6: 165307820608
A7: 2020 | B7: 15730996387 | C7: 435479892 | D7: 441621445 | E7: 16608097724 | I7: 158951615015 | J7: 3050392200 | K7: 3305813393 | L7: 165307820608
A8: 2021 | B8: 17255750754 | C8: 468147127 | D8: 320621854 | E8: 18044519735 | I8: 158951615015 | J8: 3050392200 | K8: 3305813393 | L8: 165307820608
A9: 2022 | B9: 18225123162 | C9: 454349188 | D9: 372340413 | E9: 19051812763 | H9: 43101 | I9: 1384988329 | J9: 31803799 | K9: 11758628 | L9: 1428550756
A10: 2023 | B10: 19634207642 | C10: 493035918 | D10: 590744405 | E10: 20717987965 | H10: 43132 | I10: 1257524467 | J10: 28296030 | K10: 15457621 | L10: 1301278118
A11: 2024 | B11: 20790006780 | C11: 387132522 | D11: 584843349 | E11: 21761982651 | H11: 43160 | I11: 1412228233 | J11: 28445622 | K11: 21540265 | L11: 1462214120
A12: 2025 | B12: 20272607349 | C12: 63656006 | D12: 180742650 | E12: 20517006005 | H12: 43191 | I12: 1413724796 | J12: 31753453 | K12: 19960865 | L12: 1465439114
A13: 2026 | B13: 12246738431 | C13: 18371813 | D13: 74479274 | E13: 12339589518 | H13: 43221 | I13: 1495406988 | J13: 31714034 | K13: 20536351 | L13: 1547657373
A14: Grand Total | B14: 158951615015 | C14: 3050392200 | D14: 3305813393 | E14: 165307820608 | H14: 43252 | I14: 1445468145 | J14: 28811262 | K14: 16659028 | L14: 1490938435
H15: 43282 | I15: 1554106812 | J15: 29674375 | K15: 9461417 | L15: 1593242604
H16: 43313 | I16: 1568635112 | J16: 29795498 | K16: 37566921 | L16: 1635997531
H17: 43344 | I17: 1426147420 | J17: 22397593 | K17: 20031105 | L17: 1468576118
H18: 43374 | I18: 1509655932 | J18: 0 | K18: 44305644 | L18: 1553961576
H19: 43405 | I19: 1452005038 | J19: 11371102 | K19: 28200556 | L19: 1491576696
H20: 43435 | I20: 1521993305 | J20: 35783869 | K20: 59950113 | L20: 1617727287
H21: 43466 | I21: 1339300927 | J21: 27498052 | K21: 13000599 | L21: 1379799578
H22: 43497 | I22: 1323635451 | J22: 33386661 | K22: 15164025 | L22: 1372186137
H23: 43525 | I23: 1398203645 | J23: 32948386 | K23: 26904896 | L23: 1458056927
H24: 43556 | I24: 1471829620 | J24: 35712304 | K24: 39118408 | L24: 1546660332
H25: 43586 | I25: 1514860264 | J25: 36623654 | K25: 19814613 | L25: 1571298531
H26: 43617 | I26: 1455128720 | J26: 35745741 | K26: 48361330 | L26: 1539235791
... H112: Grand Total | I112: 158951615015 | J112: 3050392200 | K112: 3305813393 | L112: 165307820608

Sheet Inputs
A1: Alaska Air Group Decarbonization Model — Inputs
A3: USER CONTROLS | B3: Value | C3: Units | D3: Model role | E3: Source / note
A4: Business activity adjustment vs FAA | B4: 0 | C4: % / year | D4: Adjusts FAA system ASM baseline; drives physical operating scale | E4: 0% = FAA baseline
A5: Operational efficiency adjustment vs EIA | B5: 0 | C5: % / year | D5: Adjusts EIA aircraft-efficiency baseline; drives fuel burn per unit activity | E5: 0% = EIA baseline
A6: SAF share in 2030 | B6: 0.1 | C6: % of liquid jet fuel | D6: 2030 SAF target endpoint | E6: Scenario input
A7: SAF share in 2040 | B7: 0.6 | C7: % of liquid jet fuel | D7: 2040 SAF target endpoint | E7: Scenario input; capped at 100%
A8: SAF lifecycle GHG reduction | B8: 0.8 | C8: % vs conventional | D8: Reduces lifecycle GHG intensity of SAF gallons | E8: Alaska states SAF can reduce lifecycle emissions by up to ~80%
A9: SAF market premium vs conventional | B9: 1 | C9: % premium | D9: Market SAF price before third-party support | E9: Scenario input; no universal transparent SAF spot price
A10: Corporate / partner share of SAF premium | B10: 0 | C10: % of SAF premium | D10: Reduces Alaska's net SAF premium; does not change physical SAF use | E10: Represents Scope 3 / book-and-claim / offtake support
A11: Fleet renewal share by 2040 | B11: 0 | C11: % of 2025 fleet-equivalent | D11: Incremental fleet benefit beyond EIA baseline | E11: Scenario input; 0% avoids double counting
A12: Ground equipment electrification by 2040 | B12: 0 | C12: % of vehicle emissions | D12: Reduces Scope 1 vehicle emissions | E12: Scenario input
A13: Novel propulsion share by 2040 | B13: 0 | C13: % of aircraft activity | D13: Displaces liquid-fuel aircraft activity with zero-carbon propulsion proxy | E13: Scenario input
A14: Carbon planning price | B14: 200 | C14: $ / tCO2e | D14: Single price applied to modeled residual emissions for 2040 closure cost | E14: Deliberately simple planning rate; carbon-market detail retained in assumptions/context
A15: Catalytic Capital | B15: 0 | C15: % of projected revenue | D15: Strategic investment that increases future SAF capacity after a lag | E15: Revenue-based control for usability; supply effect only
A16: SAF supply case | B16: Base | C16: Base / Conservative | D16: Selects published 2035 SAF production case | E16: Base = Rystad 190k bpd; Conservative = 110k bpd
A17: Post-2035 SAF supply growth | B17: 0.1 | C17: % / year | D17: Explicit growth after last published 2035 production anchor | E17: 0% default avoids hidden extrapolation
A20: BACKEND ASSUMPTIONS / PUBLISHED ANCHORS | B20: Value | C20: Units | D20: Use | E20: Source / note
A21: Fuel-burn advantage of renewed fleet | B21: 0.2 | C21: % vs replaced aircraft | D21: Multiplied by fleet-renewal share | E21: Alaska cites newer aircraft as ~15%–25% more efficient per seat; midpoint proxy
A22: Residual emissions neutralized in 2040 | B22: 1 | C22: % | D22: Share of modeled residual neutralized | E22: Net-zero closure assumption
A23: Model base year | B23: 2025 | C23: year | D23: Scenario start | E23: 2025 Alaska reporting year
A24: 2030 target year | B24: 2030 | C24: year | D24: Near-term target | E24: Alaska 2030 intensity goal
A25: 2040 net-zero year | B25: 2040 | C25: year | D25: Long-term target | E25: Alaska net-zero ambition
A26: SAF capacity capital-intensity proxy | B26: 14.666667 | C26: $ invested / annual gallon capacity | D26: Converts matured catalytic capital into incremental annual SAF capacity | E26: DOE: >$44B investment associated with >3B gal/yr announced 2030 capacity
A27: Catalytic capital deployment lag | B27: 3 | C27: years | D27: Delay before investment adds modeled capacity | E27: Stylized model assumption
A28: U.S. SAF probable production — 2030 | B28: 2048980612 | C28: gallons / year | D28: Base 2030 production anchor | E28: Peer-reviewed probable-production estimate
A29: U.S. SAF announced capacity — 2030 | B29: 3000000000 | C29: gallons / year | D29: Upper reference only | E29: DOE announced project capacity; not treated as realized production
A30: U.S. SAF production — 2035 base | B30: 2912700000 | C30: gallons / year | D30: Base 2035 production anchor | E30: Rystad base case: 190,000 bpd × 42 × 365
A31: U.S. SAF production — 2035 conservative | B31: 1686300000 | C31: gallons / year | D31: Conservative 2035 production anchor | E31: Rystad low case: 110,000 bpd × 42 × 365
A32: CORSIA reference price midpoint | B32: 59 | C32: $ / tCO2e | D32: Carbon-market context only | E32: MSCI 2033–35 range $27–$91/t midpoint
A33: Durable removal planning benchmark | B33: 200 | C33: $ / tCO2e | D33: Carbon-market context only | E33: Rounded planning rate near high-integrity removal market estimates; active model uses user Carbon planning price
A36: FAA forecast | B36: https://www.faa.gov/data_research/aviation/aerospace_forecasts/FY_2026-2046_Full_Forecast_Document_Tables.pdf
A37: EIA AEO | B37: https://www.eia.gov/outlooks/aeo/
A38: DOE SAF Liftoff | B38: https://www.energy.gov/articles/us-department-energy-releases-new-report-pathways-commercial-liftoff-sustainable-aviation
A39: 2030 SAF probable production | B39: https://www.sciencedirect.com/science/article/pii/S0961953425009274
A40: 2035 SAF cases | B40: https://www.rystadenergy.com/news/booming-biofuels-us-diesel-sustainable-aviation-fuel
A41: MSCI CORSIA | B41: https://www.msci.com/research-and-insights/paper/corsia-costs-and-implications-for-the-airline-industry
A42: Nasdaq/Puro context | B42: https://www.nasdaq.com/products/european-markets/carbon-removal-platform

Sheet Model
A1: Year | B1: Years From Base | C1: Business Activity Index | D1: Operational Efficiency Index | E1: Fleet Renewal Share | F1: Fleet Fuel Factor | G1: Novel Propulsion Share | H1: Pre-Propulsion Fuel Gallons | I1: Liquid Jet Fuel Gallons | J1: Target SAF Share | K1: Target SAF Gallons | L1: U.S. SAF Availability | M1: Market Capture Required | N1: SAF Supply Gap | O1: Effective SAF Share | P1: Effective SAF Gallons | Q1: Conventional Gallons | R1: Conventional Fuel $/gal | S1: SAF Market $/gal | T1: Alaska Net SAF $/gal | U1: Fuel Cost – No SAF | V1: Fuel Cost – With SAF | W1: Net Incremental SAF Cost | X1: Corporate / Partner Contribution | Y1: Projected Revenue | Z1: SAF Cost / Revenue | AA1: Carbon Mix Factor | AB1: Aircraft GHG Intensity (MtCO2e / 1,000 RTM) | AC1: Reduction vs 2019 | AD1: 2030 Target Low | AE1: 2030 Target High | AF1: 2040 Net Zero | AG1: Aircraft Emissions (tCO2e) | AH1: Ground Electrification Share | AI1: Vehicle Emissions (tCO2e) | AJ1: Facility Heating Emissions (tCO2e) | AK1: Scope 2 Market Emissions (tCO2e) | AL1: Operational Residual Emissions (tCO2e) | AM1: Carbon Planning Price | AN1: Carbon Closure Cost | AO1: Total Modeled Decarb Premium | AP1: Decarb Cost / Revenue
A2: 2025 | B2: =A2-Inputs!$B$23 -> 0 | C2: =INDEX('FAA Forecast'!$C$4:$C$19,MATCH(A2,'FAA Forecast'!$A$4:$A$19,0))*(1+Inputs!$B$4)^B2 -> 1 | D2: =INDEX(EIA_AEO!$E$2:$E$27,MATCH(A2,EIA_AEO!$A$2:$A$27,0))*(1+Inputs!$B$5)^B2 -> 1 | E2: =MIN(1,MAX(0,Inputs!$B$11*B2/(Inputs!$B$25-Inputs!$B$23))) -> 0 | F2: =1-E2*Inputs!$B$21 -> 1 | G2: =MIN(1,MAX(0,Inputs!$B$13*B2/(Inputs!$B$25-Inputs!$B$23))) -> 0 | H2: ='Alaska Base'!$C$6*C2/D2*F2 -> 1146000000 | I2: {=H2*(1-G2)} -> 1146000000 | J2: =MIN(1,MAX(0,IF(A2<=Inputs!$B$24,'Alaska Base'!$C$19+(Inputs!$B$6-'Alaska Base'!$C$19)*((A2-Inputs!$B$23)/(Inputs!$B$24-Inputs!$B$23)),Inputs!$B$6+(Inputs!$B$7-Inputs!$B$6)*((A2-Inputs!$B$24)/(Inputs!$B$25-Inputs!$B$24))))) -> 0.0095036161 | K2: =I2*J2 -> 10891144 | L2: =INDEX('SAF Supply'!$L$4:$L$26,MATCH(A2,'SAF Supply'!$A$4:$A$26,0)) -> 287728509 | M2: =IF(L2=0,NA(),K2/L2) -> 0.037852155 | N2: =MAX(0,K2-L2) -> 0 | O2: =IF(I2=0,0,MIN(J2,L2/I2)) -> 0.0095036161 | P2: =I2*O2 -> 10891144 | Q2: =I2-P2 -> 1135108856 | R2: ='Alaska Base'!$C$7*INDEX(EIA_AEO!$C$2:$C$27,MATCH(A2,EIA_AEO!$A$2:$A$27,0)) -> 2.51 | S2: =R2*(1+Inputs!$B$9) -> 5.02 | T2: =R2*(1+Inputs!$B$9*(1-Inputs!$B$10)) -> 5.02 | U2: =I2*R2 -> 2.87646e+09 | V2: =Q2*R2+P2*T2 -> 2.9037968e+09 | W2: =V2-U2 -> 27336771 | X2: =P2*R2*Inputs!$B$9*Inputs!$B$10 -> 0 | Y2: ='Alaska Base'!$C$8*C2 -> 14239000000 | Z2: =W2/Y2 -> 0.0019198519 | AA2: =1-O2*Inputs!$B$8 -> 0.99239711 | AB2: ='Alaska Base'!$C$3/D2*F2*(AA2/(1-'Alaska Base'!$C$19*Inputs!$B$8))*(1-G2) -> 1.33 | AC2: =1-AB2/'Alaska Base'!$C$2 -> 0.043165468 | AG2: =AB2*'Alaska Base'!$C$18*C2/1000 -> 10428326 | AH2: =MIN(1,MAX(0,Inputs!$B$12*B2/(Inputs!$B$25-Inputs!$B$23))) -> 0 | AI2: ='Alaska Base'!$C$13*C2*(1-AH2) -> 13789 | AJ2: ='Alaska Base'!$C$14*C2 -> 6385 | AK2: ='Alaska Base'!$C$16*C2 -> 13321 | AL2: =AG2+AI2+AJ2+AK2 -> 10461821 | AM2: =Inputs!$B$14 -> 200 | AN2: =IF(A2=Inputs!$B$25,AL2*AM2*Inputs!$B$22,0) -> 0 | AO2: =W2+AN2 -> 27336771 | AP2: =AO2/Y2 -> 0.0019198519
A3: 2026 | B3: 1 | C3: =INDEX('FAA Forecast'!$C$4:$C$19,MATCH(A3,'FAA Forecast'!$A$4:$A$19,0))*(1+Inputs!$B$4)^B3 -> 1.0220364 | D3: =INDEX(EIA_AEO!$E$2:$E$27,MATCH(A3,EIA_AEO!$A$2:$A$27,0))*(1+Inputs!$B$5)^B3 -> 1.0078635 | E3: =MIN(1,MAX(0,Inputs!$B$11*B3/(Inputs!$B$25-Inputs!$B$23))) -> 0 | F3: =1-E3*Inputs!$B$21 -> 1 | G3: 0 | H3: 1.1621154e+09 | I3: {=H3*(1-G3)} -> 1.1621154e+09 | J3: =MIN(1,MAX(0,IF(A3<=Inputs!$B$24,'Alaska Base'!$C$19+(Inputs!$B$6-'Alaska Base'!$C$19)*((A3-Inputs!$B$23)/(Inputs!$B$24-Inputs!$B$23)),Inputs!$B$6+(Inputs!$B$7-Inputs!$B$6)*((A3-Inputs!$B$24)/(Inputs!$B$25-Inputs!$B$24))))) -> 0.027602893 | K3: =I3*J3 -> 32077747 | L3: 4.2608269e+08 | M3: =IF(L3=0,NA(),K3/L3) -> 0.075285263 | N3: =MAX(0,K3-L3) -> 0 | O3: =IF(I3=0,0,MIN(J3,L3/I3)) -> 0.027602893 | P3: =I3*O3 -> 32077747 | Q3: =I3-P3 -> 1.1300377e+09 | R3: ='Alaska Base'!$C$7*INDEX(EIA_AEO!$C$2:$C$27,MATCH(A3,EIA_AEO!$A$2:$A$27,0)) -> 2.2385275 | S3: =R3*(1+Inputs!$B$9) -> 4.4770551 | T3: =R3*(1+Inputs!$B$9*(1-Inputs!$B$10)) -> 4.4770551 | U3: =I3*R3 -> 2.6014273e+09 | V3: =Q3*R3+P3*T3 -> 2.6732343e+09 | W3: =V3-U3 -> 71806920 | X3: =P3*R3*Inputs!$B$9*Inputs!$B$10 -> 0 | Y3: ='Alaska Base'!$C$8*C3 -> 1.4552776e+10 | Z3: =W3/Y3 -> 0.0049342422 | AA3: =1-O3*Inputs!$B$8 -> 0.97791769 | AB3: ='Alaska Base'!$C$3/D3*F3*(AA3/(1-'Alaska Base'!$C$19*Inputs!$B$8))*(1-G3) -> 1.3003694 | AC3: =1-AB3/'Alaska Base'!$C$2 -> 0.064482434 | AG3: =AB3*'Alaska Base'!$C$18*C3/1000 -> 10420680 | AH3: =MIN(1,MAX(0,Inputs!$B$12*B3/(Inputs!$B$25-Inputs!$B$23))) -> 0 | AI3: ='Alaska Base'!$C$13*C3*(1-AH3) -> 14092.859 | AJ3: ='Alaska Base'!$C$14*C3 -> 6525.7022 | AK3: ='Alaska Base'!$C$16*C3 -> 13614.546 | AL3: =AG3+AI3+AJ3+AK3 -> 10454913 | AM3: =Inputs!$B$14 -> 200 | AN3: =IF(A3=Inputs!$B$25,AL3*AM3*Inputs!$B$22,0) -> 0 | AO3: =W3+AN3 -> 71806920 | AP3: =AO3/Y3 -> 0.0049342422
A4: 2027 | B4: 2 | C4: =INDEX('FAA Forecast'!$C$4:$C$19,MATCH(A4,'FAA Forecast'!$A$4:$A$19,0))*(1+Inputs!$B$4)^B4 -> 1.0464028 | D4: =INDEX(EIA_AEO!$E$2:$E$27,MATCH(A4,EIA_AEO!$A$2:$A$27,0))*(1+Inputs!$B$5)^B4 -> 1.0158019 | E4: =MIN(1,MAX(0,Inputs!$B$11*B4/(Inputs!$B$25-Inputs!$B$23))) -> 0 | F4: =1-E4*Inputs!$B$21 -> 1 | G4: 0 | H4: 1.1805231e+09 | I4: {=H4*(1-G4)} -> 1.1805231e+09 | J4: =MIN(1,MAX(0,IF(A4<=Inputs!$B$24,'Alaska Base'!$C$19+(Inputs!$B$6-'Alaska Base'!$C$19)*((A4-Inputs!$B$23)/(Inputs!$B$24-Inputs!$B$23)),Inputs!$B$6+(Inputs!$B$7-Inputs!$B$6)*((A4-Inputs!$B$24)/(Inputs!$B$25-Inputs!$B$24))))) -> 0.04570217 | K4: =I4*J4 -> 53952468 | L4: 6.3096443e+08 | M4: =IF(L4=0,NA(),K4/L4) -> 0.08550794 | N4: =MAX(0,K4-L4) -> 0 | O4: =IF(I4=0,0,MIN(J4,L4/I4)) -> 0.04570217 | P4: =I4*O4 -> 53952468 | Q4: =I4-P4 -> 1.1265707e+09 | R4: ='Alaska Base'!$C$7*INDEX(EIA_AEO!$C$2:$C$27,MATCH(A4,EIA_AEO!$A$2:$A$27,0)) -> 2.4008773 | S4: =R4*(1+Inputs!$B$9) -> 4.8017547 | T4: =R4*(1+Inputs!$B$9*(1-Inputs!$B$10)) -> 4.8017547 | U4: =I4*R4 -> 2.8342912e+09 | V4: =Q4*R4+P4*T4 -> 2.9638245e+09 | W4: =V4-U4 -> 1.2953326e+08 | X4: =P4*R4*Inputs!$B$9*Inputs!$B$10 -> 0 | Y4: ='Alaska Base'!$C$8*C4 -> 1.489973e+10 | Z4: =W4/Y4 -> 0.0086936647 | AA4: =1-O4*Inputs!$B$8 -> 0.96343826 | AB4: ='Alaska Base'!$C$3/D4*F4*(AA4/(1-'Alaska Base'!$C$19*Inputs!$B$8))*(1-G4) -> 1.2711038 | AC4: =1-AB4/'Alaska Base'!$C$2 -> 0.085536842 | AG4: =AB4*'Alaska Base'!$C$18*C4/1000 -> 10429005 | AH4: =MIN(1,MAX(0,Inputs!$B$12*B4/(Inputs!$B$25-Inputs!$B$23))) -> 0 | AI4: ='Alaska Base'!$C$13*C4*(1-AH4) -> 14428.849 | AJ4: ='Alaska Base'!$C$14*C4 -> 6681.2822 | AK4: ='Alaska Base'!$C$16*C4 -> 13939.132 | AL4: =AG4+AI4+AJ4+AK4 -> 10464054 | AM4: =Inputs!$B$14 -> 200 | AN4: =IF(A4=Inputs!$B$25,AL4*AM4*Inputs!$B$22,0) -> 0 | AO4: =W4+AN4 -> 1.2953326e+08 | AP4: =AO4/Y4 -> 0.0086936647
A5: 2028 | B5: 3 | C5: =INDEX('FAA Forecast'!$C$4:$C$19,MATCH(A5,'FAA Forecast'!$A$4:$A$19,0))*(1+Inputs!$B$4)^B5 -> 1.0713503 | D5: =INDEX(EIA_AEO!$E$2:$E$27,MATCH(A5,EIA_AEO!$A$2:$A$27,0))*(1+Inputs!$B$5)^B5 -> 1.0239278 | E5: =MIN(1,MAX(0,Inputs!$B$11*B5/(Inputs!$B$25-Inputs!$B$23))) -> 0 | F5: =1-E5*Inputs!$B$21 -> 1 | G5: 0 | H5: 1.1990762e+09 | I5: {=H5*(1-G5)} -> 1.1990762e+09 | J5: =MIN(1,MAX(0,IF(A5<=Inputs!$B$24,'Alaska Base'!$C$19+(Inputs!$B$6-'Alaska Base'!$C$19)*((A5-Inputs!$B$23)/(Inputs!$B$24-Inputs!$B$23)),Inputs!$B$6+(Inputs!$B$7-Inputs!$B$6)*((A5-Inputs!$B$24)/(Inputs!$B$25-Inputs!$B$24))))) -> 0.063801446 | K5: =I5*J5 -> 76502795 | L5: 9.3436351e+08 | M5: =IF(L5=0,NA(),K5/L5) -> 0.081876908 | N5: =MAX(0,K5-L5) -> 0 | O5: =IF(I5=0,0,MIN(J5,L5/I5)) -> 0.063801446 | P5: =I5*O5 -> 76502795 | Q5: =I5-P5 -> 1.1225734e+09 | R5: ='Alaska Base'!$C$7*INDEX(EIA_AEO!$C$2:$C$27,MATCH(A5,EIA_AEO!$A$2:$A$27,0)) -> 2.469226 | S5: =R5*(1+Inputs!$B$9) -> 4.9384519 | T5: =R5*(1+Inputs!$B$9*(1-Inputs!$B$10)) -> 4.9384519 | U5: =I5*R5 -> 2.96079e+09 | V5: =Q5*R5+P5*T5 -> 3.1496927e+09 | W5: =V5-U5 -> 1.8890269e+08 | X5: =P5*R5*Inputs!$B$9*Inputs!$B$10 -> 0 | Y5: ='Alaska Base'!$C$8*C5 -> 1.5254956e+10 | Z5: =W5/Y5 -> 0.012383037 | AA5: =1-O5*Inputs!$B$8 -> 0.94895884 | AB5: ='Alaska Base'!$C$3/D5*F5*(AA5/(1-'Alaska Base'!$C$19*Inputs!$B$8))*(1-G5) -> 1.2420647 | AC5: =1-AB5/'Alaska Base'!$C$2 -> 0.10642829 | AG5: =AB5*'Alaska Base'!$C$18*C5/1000 -> 10433707 | AH5: =MIN(1,MAX(0,Inputs!$B$12*B5/(Inputs!$B$25-Inputs!$B$23))) -> 0 | AI5: ='Alaska Base'!$C$13*C5*(1-AH5) -> 14772.849 | AJ5: ='Alaska Base'!$C$14*C5 -> 6840.5714 | AK5: ='Alaska Base'!$C$16*C5 -> 14271.457 | AL5: =AG5+AI5+AJ5+AK5 -> 10469592 | AM5: =Inputs!$B$14 -> 200 | AN5: =IF(A5=Inputs!$B$25,AL5*AM5*Inputs!$B$22,0) -> 0 | AO5: =W5+AN5 -> 1.8890269e+08 | AP5: =AO5/Y5 -> 0.012383037
A6: 2029 | B6: 4 | C6: =INDEX('FAA Forecast'!$C$4:$C$19,MATCH(A6,'FAA Forecast'!$A$4:$A$19,0))*(1+Inputs!$B$4)^B6 -> 1.0968924 | D6: =INDEX(EIA_AEO!$E$2:$E$27,MATCH(A6,EIA_AEO!$A$2:$A$27,0))*(1+Inputs!$B$5)^B6 -> 1.0317824 | E6: =MIN(1,MAX(0,Inputs!$B$11*B6/(Inputs!$B$25-Inputs!$B$23))) -> 0 | F6: =1-E6*Inputs!$B$21 -> 1 | G6: 0 | H6: 1.2183176e+09 | I6: {=H6*(1-G6)} -> 1.2183176e+09 | J6: =MIN(1,MAX(0,IF(A6<=Inputs!$B$24,'Alaska Base'!$C$19+(Inputs!$B$6-'Alaska Base'!$C$19)*((A6-Inputs!$B$23)/(Inputs!$B$24-Inputs!$B$23)),Inputs!$B$6+(Inputs!$B$7-Inputs!$B$6)*((A6-Inputs!$B$24)/(Inputs!$B$25-Inputs!$B$24))))) -> 0.081900723 | K6: =I6*J6 -> 99781096 | L6: 1.3836519e+09 | M6: =IF(L6=0,NA(),K6/L6) -> 0.072114303 | N6: =MAX(0,K6-L6) -> 0 | O6: =IF(I6=0,0,MIN(J6,L6/I6)) -> 0.081900723 | P6: =I6*O6 -> 99781096 | Q6: =I6-P6 -> 1.1185365e+09 | R6: ='Alaska Base'!$C$7*INDEX(EIA_AEO!$C$2:$C$27,MATCH(A6,EIA_AEO!$A$2:$A$27,0)) -> 2.5288683 | S6: =R6*(1+Inputs!$B$9) -> 5.0577366 | T6: =R6*(1+Inputs!$B$9*(1-Inputs!$B$10)) -> 5.0577366 | U6: =I6*R6 -> 3.0809649e+09 | V6: =Q6*R6+P6*T6 -> 3.3332981e+09 | W6: =V6-U6 -> 2.5233325e+08 | X6: =P6*R6*Inputs!$B$9*Inputs!$B$10 -> 0 | Y6: ='Alaska Base'!$C$8*C6 -> 1.5618651e+10 | Z6: =W6/Y6 -> 0.016155892 | AA6: =1-O6*Inputs!$B$8 -> 0.93447942 | AB6: ='Alaska Base'!$C$3/D6*F6*(AA6/(1-'Alaska Base'!$C$19*Inputs!$B$8))*(1-G6) -> 1.2138018 | AC6: =1-AB6/'Alaska Base'!$C$2 -> 0.12676132 | AG6: =AB6*'Alaska Base'!$C$18*C6/1000 -> 10439381 | AH6: =MIN(1,MAX(0,Inputs!$B$12*B6/(Inputs!$B$25-Inputs!$B$23))) -> 0 | AI6: ='Alaska Base'!$C$13*C6*(1-AH6) -> 15125.05 | AJ6: ='Alaska Base'!$C$14*C6 -> 7003.6582 | AK6: ='Alaska Base'!$C$16*C6 -> 14611.704 | AL6: =AG6+AI6+AJ6+AK6 -> 10476122 | AM6: =Inputs!$B$14 -> 200 | AN6: =IF(A6=Inputs!$B$25,AL6*AM6*Inputs!$B$22,0) -> 0 | AO6: =W6+AN6 -> 2.5233325e+08 | AP6: =AO6/Y6 -> 0.016155892
A7: 2030 | B7: 5 | C7: =INDEX('FAA Forecast'!$C$4:$C$19,MATCH(A7,'FAA Forecast'!$A$4:$A$19,0))*(1+Inputs!$B$4)^B7 -> 1.1230436 | D7: =INDEX(EIA_AEO!$E$2:$E$27,MATCH(A7,EIA_AEO!$A$2:$A$27,0))*(1+Inputs!$B$5)^B7 -> 1.0397556 | E7: =MIN(1,MAX(0,Inputs!$B$11*B7/(Inputs!$B$25-Inputs!$B$23))) -> 0 | F7: =1-E7*Inputs!$B$21 -> 1 | G7: 0 | H7: 1.2377986e+09 | I7: {=H7*(1-G7)} -> 1.2377986e+09 | J7: =MIN(1,MAX(0,IF(A7<=Inputs!$B$24,'Alaska Base'!$C$19+(Inputs!$B$6-'Alaska Base'!$C$19)*((A7-Inputs!$B$23)/(Inputs!$B$24-Inputs!$B$23)),Inputs!$B$6+(Inputs!$B$7-Inputs!$B$6)*((A7-Inputs!$B$24)/(Inputs!$B$25-Inputs!$B$24))))) -> 0.1 | K7: =I7*J7 -> 1.2377986e+08 | L7: 2048980612 | M7: =IF(L7=0,NA(),K7/L7) -> 0.060410457 | N7: =MAX(0,K7-L7) -> 0 | O7: =IF(I7=0,0,MIN(J7,L7/I7)) -> 0.1 | P7: =I7*O7 -> 1.2377986e+08 | Q7: =I7-P7 -> 1.1140187e+09 | R7: ='Alaska Base'!$C$7*INDEX(EIA_AEO!$C$2:$C$27,MATCH(A7,EIA_AEO!$A$2:$A$27,0)) -> 2.5419344 | S7: =R7*(1+Inputs!$B$9) -> 5.0838689 | T7: =R7*(1+Inputs!$B$9*(1-Inputs!$B$10)) -> 5.0838689 | U7: =I7*R7 -> 3.1464028e+09 | V7: =Q7*R7+P7*T7 -> 3.461043e+09 | W7: =V7-U7 -> 3.1464028e+08 | X7: =P7*R7*Inputs!$B$9*Inputs!$B$10 -> 0 | Y7: ='Alaska Base'!$C$8*C7 -> 1.5991017e+10 | Z7: =W7/Y7 -> 0.019676064 | AA7: =1-O7*Inputs!$B$8 -> 0.92 | AB7: ='Alaska Base'!$C$3/D7*F7*(AA7/(1-'Alaska Base'!$C$19*Inputs!$B$8))*(1-G7) -> 1.1858308 | AC7: =1-AB7/'Alaska Base'!$C$2 -> 0.14688432 | AD7: ='Alaska Base'!$C$2*(1-10%) -> 1.251 | AE7: ='Alaska Base'!$C$2*(1-14%) -> 1.1954 | AG7: =AB7*'Alaska Base'!$C$18*C7/1000 -> 10441966 | AH7: =MIN(1,MAX(0,Inputs!$B$12*B7/(Inputs!$B$25-Inputs!$B$23))) -> 0 | AI7: ='Alaska Base'!$C$13*C7*(1-AH7) -> 15485.648 | AJ7: ='Alaska Base'!$C$14*C7 -> 7170.6332 | AK7: ='Alaska Base'!$C$16*C7 -> 14960.063 | AL7: =AG7+AI7+AJ7+AK7 -> 10479583 | AM7: =Inputs!$B$14 -> 200 | AN7: =IF(A7=Inputs!$B$25,AL7*AM7*Inputs!$B$22,0) -> 0 | AO7: =W7+AN7 -> 3.1464028e+08 | AP7: =AO7/Y7 -> 0.019676064
A8: 2031 | B8: 6 | C8: =INDEX('FAA Forecast'!$C$4:$C$19,MATCH(A8,'FAA Forecast'!$A$4:$A$19,0))*(1+Inputs!$B$4)^B8 -> 1.1498182 | D8: =INDEX(EIA_AEO!$E$2:$E$27,MATCH(A8,EIA_AEO!$A$2:$A$27,0))*(1+Inputs!$B$5)^B8 -> 1.047923 | E8: =MIN(1,MAX(0,Inputs!$B$11*B8/(Inputs!$B$25-Inputs!$B$23))) -> 0 | F8: =1-E8*Inputs!$B$21 -> 1 | G8: 0 | H8: 1.2574317e+09 | I8: {=H8*(1-G8)} -> 1.2574317e+09 | J8: =MIN(1,MAX(0,IF(A8<=Inputs!$B$24,'Alaska Base'!$C$19+(Inputs!$B$6-'Alaska Base'!$C$19)*((A8-Inputs!$B$23)/(Inputs!$B$24-Inputs!$B$23)),Inputs!$B$6+(Inputs!$B$7-Inputs!$B$6)*((A8-Inputs!$B$24)/(Inputs!$B$25-Inputs!$B$24))))) -> 0.15 | K8: =I8*J8 -> 1.8861475e+08 | L8: 2.1983125e+09 | M8: =IF(L8=0,NA(),K8/L8) -> 0.085799791 | N8: =MAX(0,K8-L8) -> 0 | O8: =IF(I8=0,0,MIN(J8,L8/I8)) -> 0.15 | P8: =I8*O8 -> 1.8861475e+08 | Q8: =I8-P8 -> 1.0688169e+09 | R8: ='Alaska Base'!$C$7*INDEX(EIA_AEO!$C$2:$C$27,MATCH(A8,EIA_AEO!$A$2:$A$27,0)) -> 2.5219273 | S8: =R8*(1+Inputs!$B$9) -> 5.0438546 | T8: =R8*(1+Inputs!$B$9*(1-Inputs!$B$10)) -> 5.0438546 | U8: =I8*R8 -> 3.1711513e+09 | V8: =Q8*R8+P8*T8 -> 3.646824e+09 | W8: =V8-U8 -> 4.756727e+08 | X8: =P8*R8*Inputs!$B$9*Inputs!$B$10 -> 0 | Y8: ='Alaska Base'!$C$8*C8 -> 1.6372261e+10 | Z8: =W8/Y8 -> 0.029053574 | AA8: =1-O8*Inputs!$B$8 -> 0.88 | AB8: ='Alaska Base'!$C$3/D8*F8*(AA8/(1-'Alaska Base'!$C$19*Inputs!$B$8))*(1-G8) -> 1.1254325 | AC8: =1-AB8/'Alaska Base'!$C$2 -> 0.19033636 | AG8: =AB8*'Alaska Base'!$C$18*C8/1000 -> 10146390 | AH8: =MIN(1,MAX(0,Inputs!$B$12*B8/(Inputs!$B$25-Inputs!$B$23))) -> 0 | AI8: ='Alaska Base'!$C$13*C8*(1-AH8) -> 15854.843 | AJ8: ='Alaska Base'!$C$14*C8 -> 7341.5891 | AK8: ='Alaska Base'!$C$16*C8 -> 15316.728 | AL8: =AG8+AI8+AJ8+AK8 -> 10184904 | AM8: =Inputs!$B$14 -> 200 | AN8: =IF(A8=Inputs!$B$25,AL8*AM8*Inputs!$B$22,0) -> 0 | AO8: =W8+AN8 -> 4.756727e+08 | AP8: =AO8/Y8 -> 0.029053574
A9: 2032 | B9: 7 | C9: =INDEX('FAA Forecast'!$C$4:$C$19,MATCH(A9,'FAA Forecast'!$A$4:$A$19,0))*(1+Inputs!$B$4)^B9 -> 1.1821971 | D9: =INDEX(EIA_AEO!$E$2:$E$27,MATCH(A9,EIA_AEO!$A$2:$A$27,0))*(1+Inputs!$B$5)^B9 -> 1.0566927 | E9: =MIN(1,MAX(0,Inputs!$B$11*B9/(Inputs!$B$25-Inputs!$B$23))) -> 0 | F9: =1-E9*Inputs!$B$21 -> 1 | G9: 0 | H9: 1.2821115e+09 | I9: {=H9*(1-G9)} -> 1.2821115e+09 | J9: =MIN(1,MAX(0,IF(A9<=Inputs!$B$24,'Alaska Base'!$C$19+(Inputs!$B$6-'Alaska Base'!$C$19)*((A9-Inputs!$B$23)/(Inputs!$B$24-Inputs!$B$23)),Inputs!$B$6+(Inputs!$B$7-Inputs!$B$6)*((A9-Inputs!$B$24)/(Inputs!$B$25-Inputs!$B$24))))) -> 0.2 | K9: =I9*J9 -> 2.5642229e+08 | L9: 2.3585279e+09 | M9: =IF(L9=0,NA(),K9/L9) -> 0.10872133 | N9: =MAX(0,K9-L9) -> 0 | O9: =IF(I9=0,0,MIN(J9,L9/I9)) -> 0.2 | P9: =I9*O9 -> 2.5642229e+08 | Q9: =I9-P9 -> 1.0256892e+09 | R9: ='Alaska Base'!$C$7*INDEX(EIA_AEO!$C$2:$C$27,MATCH(A9,EIA_AEO!$A$2:$A$27,0)) -> 2.5264374 | S9: =R9*(1+Inputs!$B$9) -> 5.0528749 | T9: =R9*(1+Inputs!$B$9*(1-Inputs!$B$10)) -> 5.0528749 | U9: =I9*R9 -> 3.2391744e+09 | V9: =Q9*R9+P9*T9 -> 3.8870093e+09 | W9: =V9-U9 -> 6.4783488e+08 | X9: =P9*R9*Inputs!$B$9*Inputs!$B$10 -> 0 | Y9: ='Alaska Base'!$C$8*C9 -> 1.6833304e+10 | Z9: =W9/Y9 -> 0.038485307 | AA9: =1-O9*Inputs!$B$8 -> 0.84 | AB9: ='Alaska Base'!$C$3/D9*F9*(AA9/(1-'Alaska Base'!$C$19*Inputs!$B$8))*(1-G9) -> 1.0653608 | AC9: =1-AB9/'Alaska Base'!$C$2 -> 0.23355336 | AG9: =AB9*'Alaska Base'!$C$18*C9/1000 -> 9875283.2 | AH9: =MIN(1,MAX(0,Inputs!$B$12*B9/(Inputs!$B$25-Inputs!$B$23))) -> 0 | AI9: ='Alaska Base'!$C$13*C9*(1-AH9) -> 16301.315 | AJ9: ='Alaska Base'!$C$14*C9 -> 7548.3283 | AK9: ='Alaska Base'!$C$16*C9 -> 15748.047 | AL9: =AG9+AI9+AJ9+AK9 -> 9914880.9 | AM9: =Inputs!$B$14 -> 200 | AN9: =IF(A9=Inputs!$B$25,AL9*AM9*Inputs!$B$22,0) -> 0 | AO9: =W9+AN9 -> 6.4783488e+08 | AP9: =AO9/Y9 -> 0.038485307
A10: 2033 | B10: 8 | C10: =INDEX('FAA Forecast'!$C$4:$C$19,MATCH(A10,'FAA Forecast'!$A$4:$A$19,0))*(1+Inputs!$B$4)^B10 -> 1.2154877 | D10: =INDEX(EIA_AEO!$E$2:$E$27,MATCH(A10,EIA_AEO!$A$2:$A$27,0))*(1+Inputs!$B$5)^B10 -> 1.0655601 | E10: =MIN(1,MAX(0,Inputs!$B$11*B10/(Inputs!$B$25-Inputs!$B$23))) -> 0 | F10: =1-E10*Inputs!$B$21 -> 1 | G10: 0 | H10: 1.3072458e+09 | I10: {=H10*(1-G10)} -> 1.3072458e+09 | J10: =MIN(1,MAX(0,IF(A10<=Inputs!$B$24,'Alaska Base'!$C$19+(Inputs!$B$6-'Alaska Base'!$C$19)*((A10-Inputs!$B$23)/(Inputs!$B$24-Inputs!$B$23)),Inputs!$B$6+(Inputs!$B$7-Inputs!$B$6)*((A10-Inputs!$B$24)/(Inputs!$B$25-Inputs!$B$24))))) -> 0.25 | K10: =I10*J10 -> 3.2681146e+08 | L10: 2.5304199e+09 | M10: =IF(L10=0,NA(),K10/L10) -> 0.12915306 | N10: =MAX(0,K10-L10) -> 0 | O10: =IF(I10=0,0,MIN(J10,L10/I10)) -> 0.25 | P10: =I10*O10 -> 3.2681146e+08 | Q10: =I10-P10 -> 9.8043439e+08 | R10: ='Alaska Base'!$C$7*INDEX(EIA_AEO!$C$2:$C$27,MATCH(A10,EIA_AEO!$A$2:$A$27,0)) -> 2.5946063 | S10: =R10*(1+Inputs!$B$9) -> 5.1892125 | T10: =R10*(1+Inputs!$B$9*(1-Inputs!$B$10)) -> 5.1892125 | U10: =I10*R10 -> 3.3917883e+09 | V10: =Q10*R10+P10*T10 -> 4.2397353e+09 | W10: =V10-U10 -> 8.4794707e+08 | X10: =P10*R10*Inputs!$B$9*Inputs!$B$10 -> 0 | Y10: ='Alaska Base'!$C$8*C10 -> 1.730733e+10 | Z10: =W10/Y10 -> 0.048993523 | AA10: =1-O10*Inputs!$B$8 -> 0.8 | AB10: ='Alaska Base'!$C$3/D10*F10*(AA10/(1-'Alaska Base'!$C$19*Inputs!$B$8))*(1-G10) -> 1.0061859 | AC10: =1-AB10/'Alaska Base'!$C$2 -> 0.27612529 | AG10: =AB10*'Alaska Base'!$C$18*C10/1000 -> 9589407 | AH10: =MIN(1,MAX(0,Inputs!$B$12*B10/(Inputs!$B$25-Inputs!$B$23))) -> 0 | AI10: ='Alaska Base'!$C$13*C10*(1-AH10) -> 16760.361 | AJ10: ='Alaska Base'!$C$14*C10 -> 7760.8893 | AK10: ='Alaska Base'!$C$16*C10 -> 16191.512 | AL10: =AG10+AI10+AJ10+AK10 -> 9630119.7 | AM10: =Inputs!$B$14 -> 200 | AN10: =IF(A10=Inputs!$B$25,AL10*AM10*Inputs!$B$22,0) -> 0 | AO10: =W10+AN10 -> 8.4794707e+08 | AP10: =AO10/Y10 -> 0.048993523
A11: 2034 | B11: 9 | C11: =INDEX('FAA Forecast'!$C$4:$C$19,MATCH(A11,'FAA Forecast'!$A$4:$A$19,0))*(1+Inputs!$B$4)^B11 -> 1.2497159 | D11: =INDEX(EIA_AEO!$E$2:$E$27,MATCH(A11,EIA_AEO!$A$2:$A$27,0))*(1+Inputs!$B$5)^B11 -> 1.0744024 | E11: =MIN(1,MAX(0,Inputs!$B$11*B11/(Inputs!$B$25-Inputs!$B$23))) -> 0 | F11: =1-E11*Inputs!$B$21 -> 1 | G11: 0 | H11: 1.3329963e+09 | I11: {=H11*(1-G11)} -> 1.3329963e+09 | J11: =MIN(1,MAX(0,IF(A11<=Inputs!$B$24,'Alaska Base'!$C$19+(Inputs!$B$6-'Alaska Base'!$C$19)*((A11-Inputs!$B$23)/(Inputs!$B$24-Inputs!$B$23)),Inputs!$B$6+(Inputs!$B$7-Inputs!$B$6)*((A11-Inputs!$B$24)/(Inputs!$B$25-Inputs!$B$24))))) -> 0.3 | K11: =I11*J11 -> 3.9989888e+08 | L11: 2.7148396e+09 | M11: =IF(L11=0,NA(),K11/L11) -> 0.14730111 | N11: =MAX(0,K11-L11) -> 0 | O11: =IF(I11=0,0,MIN(J11,L11/I11)) -> 0.3 | P11: =I11*O11 -> 3.9989888e+08 | Q11: =I11-P11 -> 9.330974e+08 | R11: ='Alaska Base'!$C$7*INDEX(EIA_AEO!$C$2:$C$27,MATCH(A11,EIA_AEO!$A$2:$A$27,0)) -> 2.6880359 | S11: =R11*(1+Inputs!$B$9) -> 5.3760718 | T11: =R11*(1+Inputs!$B$9*(1-Inputs!$B$10)) -> 5.3760718 | U11: =I11*R11 -> 3.5831418e+09 | V11: =Q11*R11+P11*T11 -> 4.6580844e+09 | W11: =V11-U11 -> 1.0749426e+09 | X11: =P11*R11*Inputs!$B$9*Inputs!$B$10 -> 0 | Y11: ='Alaska Base'!$C$8*C11 -> 1.7794705e+10 | Z11: =W11/Y11 -> 0.060408002 | AA11: =1-O11*Inputs!$B$8 -> 0.76 | AB11: ='Alaska Base'!$C$3/D11*F11*(AA11/(1-'Alaska Base'!$C$19*Inputs!$B$8))*(1-G11) -> 0.94800968 | AC11: =1-AB11/'Alaska Base'!$C$2 -> 0.31797865 | AG11: =AB11*'Alaska Base'!$C$18*C11/1000 -> 9289386.3 | AH11: =MIN(1,MAX(0,Inputs!$B$12*B11/(Inputs!$B$25-Inputs!$B$23))) -> 0 | AI11: ='Alaska Base'!$C$13*C11*(1-AH11) -> 17232.332 | AJ11: ='Alaska Base'!$C$14*C11 -> 7979.4359 | AK11: ='Alaska Base'!$C$16*C11 -> 16647.465 | AL11: =AG11+AI11+AJ11+AK11 -> 9331245.5 | AM11: =Inputs!$B$14 -> 200 | AN11: =IF(A11=Inputs!$B$25,AL11*AM11*Inputs!$B$22,0) -> 0 | AO11: =W11+AN11 -> 1.0749426e+09 | AP11: =AO11/Y11 -> 0.060408002
A12: 2035 | B12: 10 | C12: =INDEX('FAA Forecast'!$C$4:$C$19,MATCH(A12,'FAA Forecast'!$A$4:$A$19,0))*(1+Inputs!$B$4)^B12 -> 1.2849079 | D12: =INDEX(EIA_AEO!$E$2:$E$27,MATCH(A12,EIA_AEO!$A$2:$A$27,0))*(1+Inputs!$B$5)^B12 -> 1.0832658 | E12: =MIN(1,MAX(0,Inputs!$B$11*B12/(Inputs!$B$25-Inputs!$B$23))) -> 0 | F12: =1-E12*Inputs!$B$21 -> 1 | G12: 0 | H12: 1.3593196e+09 | I12: {=H12*(1-G12)} -> 1.3593196e+09 | J12: =MIN(1,MAX(0,IF(A12<=Inputs!$B$24,'Alaska Base'!$C$19+(Inputs!$B$6-'Alaska Base'!$C$19)*((A12-Inputs!$B$23)/(Inputs!$B$24-Inputs!$B$23)),Inputs!$B$6+(Inputs!$B$7-Inputs!$B$6)*((A12-Inputs!$B$24)/(Inputs!$B$25-Inputs!$B$24))))) -> 0.35 | K12: =I12*J12 -> 4.7576185e+08 | L12: 2912700000 | M12: =IF(L12=0,NA(),K12/L12) -> 0.16334049 | N12: =MAX(0,K12-L12) -> 0 | O12: =IF(I12=0,0,MIN(J12,L12/I12)) -> 0.35 | P12: =I12*O12 -> 4.7576185e+08 | Q12: =I12-P12 -> 8.8355773e+08 | R12: ='Alaska Base'!$C$7*INDEX(EIA_AEO!$C$2:$C$27,MATCH(A12,EIA_AEO!$A$2:$A$27,0)) -> 2.7183936 | S12: =R12*(1+Inputs!$B$9) -> 5.4367872 | T12: =R12*(1+Inputs!$B$9*(1-Inputs!$B$10)) -> 5.4367872 | U12: =I12*R12 -> 3.6951656e+09 | V12: =Q12*R12+P12*T12 -> 4.9884736e+09 | W12: =V12-U12 -> 1.293308e+09 | X12: =P12*R12*Inputs!$B$9*Inputs!$B$10 -> 0 | Y12: ='Alaska Base'!$C$8*C12 -> 1.8295804e+10 | Z12: =W12/Y12 -> 0.070688777 | AA12: =1-O12*Inputs!$B$8 -> 0.72 | AB12: ='Alaska Base'!$C$3/D12*F12*(AA12/(1-'Alaska Base'!$C$19*Inputs!$B$8))*(1-G12) -> 0.89076594 | AC12: =1-AB12/'Alaska Base'!$C$2 -> 0.35916119 | AG12: =AB12*'Alaska Base'!$C$18*C12/1000 -> 8974258.2 | AH12: =MIN(1,MAX(0,Inputs!$B$12*B12/(Inputs!$B$25-Inputs!$B$23))) -> 0 | AI12: ='Alaska Base'!$C$13*C12*(1-AH12) -> 17717.595 | AJ12: ='Alaska Base'!$C$14*C12 -> 8204.1369 | AK12: ='Alaska Base'!$C$16*C12 -> 17116.258 | AL12: =AG12+AI12+AJ12+AK12 -> 9017296.2 | AM12: =Inputs!$B$14 -> 200 | AN12: =IF(A12=Inputs!$B$25,AL12*AM12*Inputs!$B$22,0) -> 0 | AO12: =W12+AN12 -> 1.293308e+09 | AP12: =AO12/Y12 -> 0.070688777
A13: 2036 | B13: 11 | C13: =INDEX('FAA Forecast'!$C$4:$C$19,MATCH(A13,'FAA Forecast'!$A$4:$A$19,0))*(1+Inputs!$B$4)^B13 -> 1.3210909 | D13: =INDEX(EIA_AEO!$E$2:$E$27,MATCH(A13,EIA_AEO!$A$2:$A$27,0))*(1+Inputs!$B$5)^B13 -> 1.0921428 | E13: =MIN(1,MAX(0,Inputs!$B$11*B13/(Inputs!$B$25-Inputs!$B$23))) -> 0 | F13: =1-E13*Inputs!$B$21 -> 1 | G13: 0 | H13: 1.3862383e+09 | I13: {=H13*(1-G13)} -> 1.3862383e+09 | J13: =MIN(1,MAX(0,IF(A13<=Inputs!$B$24,'Alaska Base'!$C$19+(Inputs!$B$6-'Alaska Base'!$C$19)*((A13-Inputs!$B$23)/(Inputs!$B$24-Inputs!$B$23)),Inputs!$B$6+(Inputs!$B$7-Inputs!$B$6)*((A13-Inputs!$B$24)/(Inputs!$B$25-Inputs!$B$24))))) -> 0.4 | K13: =I13*J13 -> 5.5449534e+08 | L13: 2912700000 | M13: =IF(L13=0,NA(),K13/L13) -> 0.19037159 | N13: =MAX(0,K13-L13) -> 0 | O13: =IF(I13=0,0,MIN(J13,L13/I13)) -> 0.4 | P13: =I13*O13 -> 5.5449534e+08 | Q13: =I13-P13 -> 8.31743e+08 | R13: ='Alaska Base'!$C$7*INDEX(EIA_AEO!$C$2:$C$27,MATCH(A13,EIA_AEO!$A$2:$A$27,0)) -> 2.7458155 | S13: =R13*(1+Inputs!$B$9) -> 5.4916311 | T13: =R13*(1+Inputs!$B$9*(1-Inputs!$B$10)) -> 5.4916311 | U13: =I13*R13 -> 3.8063548e+09 | V13: =Q13*R13+P13*T13 -> 5.3288967e+09 | W13: =V13-U13 -> 1.5225419e+09 | X13: =P13*R13*Inputs!$B$9*Inputs!$B$10 -> 0 | Y13: ='Alaska Base'!$C$8*C13 -> 1.8811013e+10 | Z13: =W13/Y13 -> 0.080938856 | AA13: =1-O13*Inputs!$B$8 -> 0.68 | AB13: ='Alaska Base'!$C$3/D13*F13*(AA13/(1-'Alaska Base'!$C$19*Inputs!$B$8))*(1-G13) -> 0.83444103 | AC13: =1-AB13/'Alaska Base'!$C$2 -> 0.39968272 | AG13: =AB13*'Alaska Base'!$C$18*C13/1000 -> 8643533.3 | AH13: =MIN(1,MAX(0,Inputs!$B$12*B13/(Inputs!$B$25-Inputs!$B$23))) -> 0 | AI13: ='Alaska Base'!$C$13*C13*(1-AH13) -> 18216.523 | AJ13: ='Alaska Base'!$C$14*C13 -> 8435.1655 | AK13: ='Alaska Base'!$C$16*C13 -> 17598.252 | AL13: =AG13+AI13+AJ13+AK13 -> 8687783.3 | AM13: =Inputs!$B$14 -> 200 | AN13: =IF(A13=Inputs!$B$25,AL13*AM13*Inputs!$B$22,0) -> 0 | AO13: =W13+AN13 -> 1.5225419e+09 | AP13: =AO13/Y13 -> 0.080938856
A14: 2037 | B14: 12 | C14: =INDEX('FAA Forecast'!$C$4:$C$19,MATCH(A14,'FAA Forecast'!$A$4:$A$19,0))*(1+Inputs!$B$4)^B14 -> 1.3543812 | D14: =INDEX(EIA_AEO!$E$2:$E$27,MATCH(A14,EIA_AEO!$A$2:$A$27,0))*(1+Inputs!$B$5)^B14 -> 1.1009696 | E14: =MIN(1,MAX(0,Inputs!$B$11*B14/(Inputs!$B$25-Inputs!$B$23))) -> 0 | F14: =1-E14*Inputs!$B$21 -> 1 | G14: 0 | H14: 1.4097764e+09 | I14: {=H14*(1-G14)} -> 1.4097764e+09 | J14: =MIN(1,MAX(0,IF(A14<=Inputs!$B$24,'Alaska Base'!$C$19+(Inputs!$B$6-'Alaska Base'!$C$19)*((A14-Inputs!$B$23)/(Inputs!$B$24-Inputs!$B$23)),Inputs!$B$6+(Inputs!$B$7-Inputs!$B$6)*((A14-Inputs!$B$24)/(Inputs!$B$25-Inputs!$B$24))))) -> 0.45 | K14: =I14*J14 -> 6.3439938e+08 | L14: 2912700000 | M14: =IF(L14=0,NA(),K14/L14) -> 0.21780457 | N14: =MAX(0,K14-L14) -> 0 | O14: =IF(I14=0,0,MIN(J14,L14/I14)) -> 0.45 | P14: =I14*O14 -> 6.3439938e+08 | Q14: =I14-P14 -> 7.7537702e+08 | R14: ='Alaska Base'!$C$7*INDEX(EIA_AEO!$C$2:$C$27,MATCH(A14,EIA_AEO!$A$2:$A$27,0)) -> 2.8377208 | S14: =R14*(1+Inputs!$B$9) -> 5.6754416 | T14: =R14*(1+Inputs!$B$9*(1-Inputs!$B$10)) -> 5.6754416 | U14: =I14*R14 -> 4.0005518e+09 | V14: =Q14*R14+P14*T14 -> 5.8008001e+09 | W14: =V14-U14 -> 1.8002483e+09 | X14: =P14*R14*Inputs!$B$9*Inputs!$B$10 -> 0 | Y14: ='Alaska Base'!$C$8*C14 -> 1.9285034e+10 | Z14: =W14/Y14 -> 0.0933495 | AA14: =1-O14*Inputs!$B$8 -> 0.64 | AB14: ='Alaska Base'!$C$3/D14*F14*(AA14/(1-'Alaska Base'!$C$19*Inputs!$B$8))*(1-G14) -> 0.77905984 | AC14: =1-AB14/'Alaska Base'!$C$2 -> 0.4395253 | AG14: =AB14*'Alaska Base'!$C$18*C14/1000 -> 8273222.4 | AH14: =MIN(1,MAX(0,Inputs!$B$12*B14/(Inputs!$B$25-Inputs!$B$23))) -> 0 | AI14: ='Alaska Base'!$C$13*C14*(1-AH14) -> 18675.563 | AJ14: ='Alaska Base'!$C$14*C14 -> 8647.7242 | AK14: ='Alaska Base'!$C$16*C14 -> 18041.712 | AL14: =AG14+AI14+AJ14+AK14 -> 8318587.4 | AM14: =Inputs!$B$14 -> 200 | AN14: =IF(A14=Inputs!$B$25,AL14*AM14*Inputs!$B$22,0) -> 0 | AO14: =W14+AN14 -> 1.8002483e+09 | AP14: =AO14/Y14 -> 0.0933495
A15: 2038 | B15: 13 | C15: =INDEX('FAA Forecast'!$C$4:$C$19,MATCH(A15,'FAA Forecast'!$A$4:$A$19,0))*(1+Inputs!$B$4)^B15 -> 1.3885104 | D15: =INDEX(EIA_AEO!$E$2:$E$27,MATCH(A15,EIA_AEO!$A$2:$A$27,0))*(1+Inputs!$B$5)^B15 -> 1.1100108 | E15: =MIN(1,MAX(0,Inputs!$B$11*B15/(Inputs!$B$25-Inputs!$B$23))) -> 0 | F15: =1-E15*Inputs!$B$21 -> 1 | G15: 0 | H15: 1.4335293e+09 | I15: {=H15*(1-G15)} -> 1.4335293e+09 | J15: =MIN(1,MAX(0,IF(A15<=Inputs!$B$24,'Alaska Base'!$C$19+(Inputs!$B$6-'Alaska Base'!$C$19)*((A15-Inputs!$B$23)/(Inputs!$B$24-Inputs!$B$23)),Inputs!$B$6+(Inputs!$B$7-Inputs!$B$6)*((A15-Inputs!$B$24)/(Inputs!$B$25-Inputs!$B$24))))) -> 0.5 | K15: =I15*J15 -> 7.1676465e+08 | L15: 2912700000 | M15: =IF(L15=0,NA(),K15/L15) -> 0.24608255 | N15: =MAX(0,K15-L15) -> 0 | O15: =IF(I15=0,0,MIN(J15,L15/I15)) -> 0.5 | P15: =I15*O15 -> 7.1676465e+08 | Q15: =I15-P15 -> 7.1676465e+08 | R15: ='Alaska Base'!$C$7*INDEX(EIA_AEO!$C$2:$C$27,MATCH(A15,EIA_AEO!$A$2:$A$27,0)) -> 2.8738181 | S15: =R15*(1+Inputs!$B$9) -> 5.7476362 | T15: =R15*(1+Inputs!$B$9*(1-Inputs!$B$10)) -> 5.7476362 | U15: =I15*R15 -> 4.1197025e+09 | V15: =Q15*R15+P15*T15 -> 6.1795537e+09 | W15: =V15-U15 -> 2.0598512e+09 | X15: =P15*R15*Inputs!$B$9*Inputs!$B$10 -> 0 | Y15: ='Alaska Base'!$C$8*C15 -> 1.9771e+10 | Z15: =W15/Y15 -> 0.10418548 | AA15: =1-O15*Inputs!$B$8 -> 0.6 | AB15: ='Alaska Base'!$C$3/D15*F15*(AA15/(1-'Alaska Base'!$C$19*Inputs!$B$8))*(1-G15) -> 0.72441963 | AC15: =1-AB15/'Alaska Base'!$C$2 -> 0.4788348 | AG15: =AB15*'Alaska Base'!$C$18*C15/1000 -> 7886827 | AH15: =MIN(1,MAX(0,Inputs!$B$12*B15/(Inputs!$B$25-Inputs!$B$23))) -> 0 | AI15: ='Alaska Base'!$C$13*C15*(1-AH15) -> 19146.17 | AJ15: ='Alaska Base'!$C$14*C15 -> 8865.6392 | AK15: ='Alaska Base'!$C$16*C15 -> 18496.348 | AL15: =AG15+AI15+AJ15+AK15 -> 7933335.2 | AM15: =Inputs!$B$14 -> 200 | AN15: =IF(A15=Inputs!$B$25,AL15*AM15*Inputs!$B$22,0) -> 0 | AO15: =W15+AN15 -> 2.0598512e+09 | AP15: =AO15/Y15 -> 0.10418548
A16: 2039 | B16: 14 | C16: =INDEX('FAA Forecast'!$C$4:$C$19,MATCH(A16,'FAA Forecast'!$A$4:$A$19,0))*(1+Inputs!$B$4)^B16 -> 1.4234997 | D16: =INDEX(EIA_AEO!$E$2:$E$27,MATCH(A16,EIA_AEO!$A$2:$A$27,0))*(1+Inputs!$B$5)^B16 -> 1.1189377 | E16: =MIN(1,MAX(0,Inputs!$B$11*B16/(Inputs!$B$25-Inputs!$B$23))) -> 0 | F16: =1-E16*Inputs!$B$21 -> 1 | G16: 0 | H16: 1.457928e+09 | I16: {=H16*(1-G16)} -> 1.457928e+09 | J16: =MIN(1,MAX(0,IF(A16<=Inputs!$B$24,'Alaska Base'!$C$19+(Inputs!$B$6-'Alaska Base'!$C$19)*((A16-Inputs!$B$23)/(Inputs!$B$24-Inputs!$B$23)),Inputs!$B$6+(Inputs!$B$7-Inputs!$B$6)*((A16-Inputs!$B$24)/(Inputs!$B$25-Inputs!$B$24))))) -> 0.55 | K16: =I16*J16 -> 8.0186041e+08 | L16: 2912700000 | M16: =IF(L16=0,NA(),K16/L16) -> 0.27529797 | N16: =MAX(0,K16-L16) -> 0 | O16: =IF(I16=0,0,MIN(J16,L16/I16)) -> 0.55 | P16: =I16*O16 -> 8.0186041e+08 | Q16: =I16-P16 -> 6.5606761e+08 | R16: ='Alaska Base'!$C$7*INDEX(EIA_AEO!$C$2:$C$27,MATCH(A16,EIA_AEO!$A$2:$A$27,0)) -> 2.9388201 | S16: =R16*(1+Inputs!$B$9) -> 5.8776402 | T16: =R16*(1+Inputs!$B$9*(1-Inputs!$B$10)) -> 5.8776402 | U16: =I16*R16 -> 4.2845881e+09 | V16: =Q16*R16+P16*T16 -> 6.6411116e+09 | W16: =V16-U16 -> 2.3565235e+09 | X16: =P16*R16*Inputs!$B$9*Inputs!$B$10 -> 0 | Y16: ='Alaska Base'!$C$8*C16 -> 2.0269212e+10 | Z16: =W16/Y16 -> 0.11626123 | AA16: =1-O16*Inputs!$B$8 -> 0.56 | AB16: ='Alaska Base'!$C$3/D16*F16*(AA16/(1-'Alaska Base'!$C$19*Inputs!$B$8))*(1-G16) -> 0.67073083 | AC16: =1-AB16/'Alaska Base'!$C$2 -> 0.51745983 | AG16: =AB16*'Alaska Base'!$C$18*C16/1000 -> 7486323.7 | AH16: =MIN(1,MAX(0,Inputs!$B$12*B16/(Inputs!$B$25-Inputs!$B$23))) -> 0 | AI16: ='Alaska Base'!$C$13*C16*(1-AH16) -> 19628.637 | AJ16: ='Alaska Base'!$C$14*C16 -> 9089.0454 | AK16: ='Alaska Base'!$C$16*C16 -> 18962.439 | AL16: =AG16+AI16+AJ16+AK16 -> 7534003.8 | AM16: =Inputs!$B$14 -> 200 | AN16: =IF(A16=Inputs!$B$25,AL16*AM16*Inputs!$B$22,0) -> 0 | AO16: =W16+AN16 -> 2.3565235e+09 | AP16: =AO16/Y16 -> 0.11626123
A17: 2040 | B17: 15 | C17: =INDEX('FAA Forecast'!$C$4:$C$19,MATCH(A17,'FAA Forecast'!$A$4:$A$19,0))*(1+Inputs!$B$4)^B17 -> 1.4593706 | D17: =INDEX(EIA_AEO!$E$2:$E$27,MATCH(A17,EIA_AEO!$A$2:$A$27,0))*(1+Inputs!$B$5)^B17 -> 1.1280637 | E17: =MIN(1,MAX(0,Inputs!$B$11*B17/(Inputs!$B$25-Inputs!$B$23))) -> 0 | F17: =1-E17*Inputs!$B$21 -> 1 | G17: 0 | H17: 1.4825747e+09 | I17: {=H17*(1-G17)} -> 1.4825747e+09 | J17: =MIN(1,MAX(0,IF(A17<=Inputs!$B$24,'Alaska Base'!$C$19+(Inputs!$B$6-'Alaska Base'!$C$19)*((A17-Inputs!$B$23)/(Inputs!$B$24-Inputs!$B$23)),Inputs!$B$6+(Inputs!$B$7-Inputs!$B$6)*((A17-Inputs!$B$24)/(Inputs!$B$25-Inputs!$B$24))))) -> 0.6 | K17: =I17*J17 -> 8.8954484e+08 | L17: 2912700000 | M17: =IF(L17=0,NA(),K17/L17) -> 0.30540215 | N17: =MAX(0,K17-L17) -> 0 | O17: =IF(I17=0,0,MIN(J17,L17/I17)) -> 0.6 | P17: =I17*O17 -> 8.8954484e+08 | Q17: =I17-P17 -> 5.930299e+08 | R17: ='Alaska Base'!$C$7*INDEX(EIA_AEO!$C$2:$C$27,MATCH(A17,EIA_AEO!$A$2:$A$27,0)) -> 2.974625 | S17: =R17*(1+Inputs!$B$9) -> 5.94925 | T17: =R17*(1+Inputs!$B$9*(1-Inputs!$B$10)) -> 5.94925 | U17: =I17*R17 -> 4.4101039e+09 | V17: =Q17*R17+P17*T17 -> 7.0561662e+09 | W17: =V17-U17 -> 2.6460623e+09 | X17: =P17*R17*Inputs!$B$9*Inputs!$B$10 -> 0 | Y17: ='Alaska Base'!$C$8*C17 -> 2.0779978e+10 | Z17: =W17/Y17 -> 0.12733711 | AA17: =1-O17*Inputs!$B$8 -> 0.52 | AB17: ='Alaska Base'!$C$3/D17*F17*(AA17/(1-'Alaska Base'!$C$19*Inputs!$B$8))*(1-G17) -> 0.61778289 | AC17: =1-AB17/'Alaska Base'!$C$2 -> 0.55555187 | AF17: 0 | AG17: =AB17*'Alaska Base'!$C$18*C17/1000 -> 7069105 | AH17: =MIN(1,MAX(0,Inputs!$B$12*B17/(Inputs!$B$25-Inputs!$B$23))) -> 0 | AI17: ='Alaska Base'!$C$13*C17*(1-AH17) -> 20123.261 | AJ17: ='Alaska Base'!$C$14*C17 -> 9318.0813 | AK17: ='Alaska Base'!$C$16*C17 -> 19440.276 | AL17: =AG17+AI17+AJ17+AK17 -> 7117986.6 | AM17: =Inputs!$B$14 -> 200 | AN17: =IF(A17=Inputs!$B$25,AL17*AM17*Inputs!$B$22,0) -> 1.4235973e+09 | AO17: =W17+AN17 -> 4.0696597e+09 | AP17: =AO17/Y17 -> 0.19584523

Sheet Outputs
A1: Decision Outputs
A3: 2030 TARGET + SAF MARKET + REVENUE BURDEN | B3: Value | C3: Units | D3: Interpretation
A4: Business Activity Index | B4: =INDEX(Model!$C$2:$C$17,MATCH(Inputs!$B$24,Model!$A$2:$A$17,0)) -> 1.1230436 | C4: index | D4: FAA system ASM baseline plus user adjustment
A5: Operational Efficiency Index | B5: =INDEX(Model!$D$2:$D$17,MATCH(Inputs!$B$24,Model!$A$2:$A$17,0)) -> 1.0397556 | C5: index | D5: EIA aircraft-efficiency baseline plus user adjustment
A6: Fleet Fuel Factor | B6: =INDEX(Model!$F$2:$F$17,MATCH(Inputs!$B$24,Model!$A$2:$A$17,0)) -> 1 | C6: factor | D6: Incremental fleet-renewal effect; 1.00 = none
A7: Novel Propulsion Share | B7: =INDEX(Model!$G$2:$G$17,MATCH(Inputs!$B$24,Model!$A$2:$A$17,0)) -> 0 | C7: % | D7: Zero-carbon propulsion proxy
A8: Target SAF Share | B8: =INDEX(Model!$J$2:$J$17,MATCH(Inputs!$B$24,Model!$A$2:$A$17,0)) -> 0.1 | C8: % | D8: User-selected 2030 endpoint
A9: Effective SAF Share | B9: =INDEX(Model!$O$2:$O$17,MATCH(Inputs!$B$24,Model!$A$2:$A$17,0)) -> 0.1 | C9: % | D9: Target share after physical U.S. supply constraint
A10: Adjusted U.S. SAF Availability | B10: =INDEX(Model!$L$2:$L$17,MATCH(Inputs!$B$24,Model!$A$2:$A$17,0)) -> 2048980612 | C10: gallons / year | D10: Selected supply case + matured catalytic capacity
A11: Target SAF Gallons | B11: =INDEX(Model!$K$2:$K$17,MATCH(Inputs!$B$24,Model!$A$2:$A$17,0)) -> 1.2377986e+08 | C11: gallons | D11: Desired Alaska SAF procurement
A12: Effective SAF Gallons | B12: =INDEX(Model!$P$2:$P$17,MATCH(Inputs!$B$24,Model!$A$2:$A$17,0)) -> 1.2377986e+08 | C12: gallons | D12: Supply-constrained Alaska SAF procurement
A13: Market Capture Required | B13: =INDEX(Model!$M$2:$M$17,MATCH(Inputs!$B$24,Model!$A$2:$A$17,0)) -> 0.060410457 | C13: % of U.S. supply | D13: Share of adjusted U.S. supply Alaska must secure
A14: SAF Supply Gap | B14: =INDEX(Model!$N$2:$N$17,MATCH(Inputs!$B$24,Model!$A$2:$A$17,0)) -> 0 | C14: gallons | D14: Shortfall if target exceeds total modeled U.S. availability
A15: Required SAF Share — 10% Goal | B15: =IF(B7>=1,0,MIN(1,MAX(0,(1-(('Alaska Base'!$C$2*(1-10%))*B5/'Alaska Base'!$C$3/B6/(1-B7)*(1-'Alaska Base'!$C$19*Inputs!$B$8)))/Inputs!$B$8))) -> 0.036799937 | C15: % | D15: Minimum effective SAF share for 10% intensity reduction
A16: Required SAF Share — 14% Goal | B16: =IF(B7>=1,0,MIN(1,MAX(0,(1-(('Alaska Base'!$C$2*(1-14%))*B5/'Alaska Base'!$C$3/B6/(1-B7)*(1-'Alaska Base'!$C$19*Inputs!$B$8)))/Inputs!$B$8))) -> 0.090719939 | C16: % | D16: Minimum effective SAF share for 14% intensity reduction
A17: Required SAF Gallons — 10% Goal | B17: =B15*INDEX(Model!$I$2:$I$17,MATCH(Inputs!$B$24,Model!$A$2:$A$17,0)) -> 45550908 | C17: gallons | D17: Physical SAF requirement for lower target
A18: Required SAF Gallons — 14% Goal | B18: =B16*INDEX(Model!$I$2:$I$17,MATCH(Inputs!$B$24,Model!$A$2:$A$17,0)) -> 1.1229301e+08 | C18: gallons | D18: Physical SAF requirement for upper target
A19: Required Market Capture — 10% Goal | B19: =IF(B10=0,NA(),B17/B10) -> 0.02223101 | C19: % of U.S. supply | D19: Required gallons / adjusted supply
A20: Required Market Capture — 14% Goal | B20: =IF(B10=0,NA(),B18/B10) -> 0.05480433 | C20: % of U.S. supply | D20: Required gallons / adjusted supply
A21: Modeled GHG Intensity | B21: =INDEX(Model!$AB$2:$AB$17,MATCH(Inputs!$B$24,Model!$A$2:$A$17,0)) -> 1.1858308 | C21: MtCO2e / 1,000 RTM | D21: Supply-constrained emissions-intensity result
A22: Reduction vs 2019 | B22: =INDEX(Model!$AC$2:$AC$17,MATCH(Inputs!$B$24,Model!$A$2:$A$17,0)) -> 0.14688432 | C22: % | D22: Reduction from 2019 baseline
A23: Target Status | B23: =IF(B21<='Alaska Base'!$C$2*(1-14%),"Meets 14% target",IF(B21<='Alaska Base'!$C$2*(1-10%),"Within 10%–14% target range","Misses 2030 target")) -> Meets 14% target | D23: 2030 target attainment
A24: Projected Revenue | B24: =INDEX(Model!$Y$2:$Y$17,MATCH(Inputs!$B$24,Model!$A$2:$A$17,0)) -> 1.5991017e+10 | C24: $ | D24: 2025 revenue scaled with business activity
A25: Net Incremental SAF Cost | B25: =INDEX(Model!$W$2:$W$17,MATCH(Inputs!$B$24,Model!$A$2:$A$17,0)) -> 3.1464028e+08 | C25: $ | D25: SAF premium borne by Alaska after partner support
A26: Corporate / Partner Contribution | B26: =INDEX(Model!$X$2:$X$17,MATCH(Inputs!$B$24,Model!$A$2:$A$17,0)) -> 0 | C26: $ | D26: Premium shifted to third-party environmental-attribute buyers
A27: SAF Cost / Revenue | B27: =INDEX(Model!$Z$2:$Z$17,MATCH(Inputs!$B$24,Model!$A$2:$A$17,0)) -> 0.019676064 | C27: % revenue | D27: Net SAF premium / projected revenue
A28: Baseline Aircraft Capital / Revenue | B28: =INDEX('Capital Allocation'!$E$4:$E$9,MATCH(2030,'Capital Allocation'!$A$4:$A$9,0)) -> 0.065661863 | C28: % revenue | D28: Disclosed capital/commitment burden normalized to revenue
A29: Known Capital + SAF + Catalytic / Revenue | B29: =INDEX('Capital Allocation'!$J$4:$J$9,MATCH(2030,'Capital Allocation'!$A$4:$A$9,0)) -> 0.085337927 | C29: % revenue | D29: Indicative modeled spending burden; not a solvency ratio
A32: 2040 NET-ZERO + REVENUE BURDEN | B32: Value | C32: Units | D32: Interpretation
A33: Business Activity Index | B33: =INDEX(Model!$C$2:$C$17,MATCH(Inputs!$B$25,Model!$A$2:$A$17,0)) -> 1.4593706 | C33: index | D33: FAA system ASM baseline plus user adjustment
A34: Operational Efficiency Index | B34: =INDEX(Model!$D$2:$D$17,MATCH(Inputs!$B$25,Model!$A$2:$A$17,0)) -> 1.1280637 | C34: index | D34: EIA aircraft-efficiency baseline plus user adjustment
A35: Fleet Renewal Share | B35: =INDEX(Model!$E$2:$E$17,MATCH(Inputs!$B$25,Model!$A$2:$A$17,0)) -> 0 | C35: % | D35: User-controlled incremental renewal share
A36: Novel Propulsion Share | B36: =INDEX(Model!$G$2:$G$17,MATCH(Inputs!$B$25,Model!$A$2:$A$17,0)) -> 0 | C36: % | D36: Zero-carbon propulsion proxy
A37: Target SAF Share | B37: =INDEX(Model!$J$2:$J$17,MATCH(Inputs!$B$25,Model!$A$2:$A$17,0)) -> 0.6 | C37: % | D37: User-selected 2040 endpoint
A38: Effective SAF Share | B38: =INDEX(Model!$O$2:$O$17,MATCH(Inputs!$B$25,Model!$A$2:$A$17,0)) -> 0.6 | C38: % | D38: Supply-constrained SAF share
A39: Adjusted U.S. SAF Availability | B39: =INDEX(Model!$L$2:$L$17,MATCH(Inputs!$B$25,Model!$A$2:$A$17,0)) -> 2912700000 | C39: gallons / year | D39: Selected 2035 case + explicit post-2035 growth + catalytic capacity
A40: Market Capture Required | B40: =INDEX(Model!$M$2:$M$17,MATCH(Inputs!$B$25,Model!$A$2:$A$17,0)) -> 0.30540215 | C40: % of U.S. supply | D40: Share of adjusted U.S. supply Alaska must secure
A41: SAF Supply Gap | B41: =INDEX(Model!$N$2:$N$17,MATCH(Inputs!$B$25,Model!$A$2:$A$17,0)) -> 0 | C41: gallons | D41: Shortfall if target exceeds modeled U.S. availability
A42: Modeled Aircraft GHG Intensity | B42: =INDEX(Model!$AB$2:$AB$17,MATCH(Inputs!$B$25,Model!$A$2:$A$17,0)) -> 0.61778289 | C42: MtCO2e / 1,000 RTM | D42: Aircraft intensity after physical levers
A43: Reduction vs 2019 | B43: =INDEX(Model!$AC$2:$AC$17,MATCH(Inputs!$B$25,Model!$A$2:$A$17,0)) -> 0.55555187 | C43: % | D43: Aircraft intensity reduction
A44: Aircraft Emissions | B44: =INDEX(Model!$AG$2:$AG$17,MATCH(Inputs!$B$25,Model!$A$2:$A$17,0)) -> 7069105 | C44: tCO2e | D44: Absolute aircraft emissions
A45: Operational Residual Emissions | B45: =INDEX(Model!$AL$2:$AL$17,MATCH(Inputs!$B$25,Model!$A$2:$A$17,0)) -> 7117986.6 | C45: tCO2e | D45: Aircraft + vehicle + facility + market-based Scope 2
A46: Carbon Planning Price | B46: =INDEX(Model!$AM$2:$AM$17,MATCH(Inputs!$B$25,Model!$A$2:$A$17,0)) -> 200 | C46: $ / tCO2e | D46: Single user-controlled planning price
A47: Carbon Closure Cost | B47: =INDEX(Model!$AN$2:$AN$17,MATCH(Inputs!$B$25,Model!$A$2:$A$17,0)) -> 1.4235973e+09 | C47: $ | D47: Residual emissions × carbon planning price × neutralization share
A48: Net Incremental SAF Cost | B48: =INDEX(Model!$W$2:$W$17,MATCH(Inputs!$B$25,Model!$A$2:$A$17,0)) -> 2.6460623e+09 | C48: $ | D48: SAF premium borne by Alaska after partner support
A49: Corporate / Partner Contribution | B49: =INDEX(Model!$X$2:$X$17,MATCH(Inputs!$B$25,Model!$A$2:$A$17,0)) -> 0 | C49: $ | D49: Third-party support for SAF environmental attribute
A50: Total Modeled Decarb Premium | B50: =INDEX(Model!$AO$2:$AO$17,MATCH(Inputs!$B$25,Model!$A$2:$A$17,0)) -> 4.0696597e+09 | C50: $ | D50: Net SAF premium + carbon closure cost
A51: Decarb Cost / Revenue | B51: =INDEX(Model!$AP$2:$AP$17,MATCH(Inputs!$B$25,Model!$A$2:$A$17,0)) -> 0.19584523 | C51: % revenue | D51: Modeled premium / projected revenue
A52: Remaining Gap After Carbon Closure | B52: =MAX(0,B45-B45*Inputs!$B$22) -> 0 | C52: tCO2e | D52: Zero at 100% neutralization assumption

Sheet Dashboard
A1: Alaska Air Group Decarbonization Scenario Dashboard
P2: Year | Q2: GHG Intensity | R2: 2030 10% | S2: 2030 14% | T2: Net Zero | V2: Year | W2: Base SAF Supply | X2: Conservative SAF Supply | Y2: Adjusted Selected Supply | Z2: Alaska Target SAF | AB2: 2030 SAF Share | AC2: Percent | AE2: 2030 Revenue Burden | AF2: Percent
P3: =Model!A2 -> 2025 | Q3: =Model!AB2 -> 1.33 | R3: ='Alaska Base'!$C$2*(1-10%) -> 1.251 | S3: ='Alaska Base'!$C$2*(1-14%) -> 1.1954 | T3: 0 | V3: ='SAF Supply'!A11 -> 2025 | W3: ='SAF Supply'!D11 -> 287728509 | X3: ='SAF Supply'!E11 -> 287728509 | Y3: ='SAF Supply'!L11 -> 287728509 | Z3: ='SAF Supply'!M11 -> 10891144 | AB3: Required — 10% | AC3: =Outputs!B15*100 -> 3.6799937 | AE3: Baseline aircraft capital | AF3: =Outputs!B28*100 -> 6.5661863
A4: 2030 Goal Test | F4: SAF Market Feasibility | K4: Economics as Share of Revenue | P4: =Model!A3 -> 2026 | Q4: =Model!AB3 -> 1.3003694 | R4: ='Alaska Base'!$C$2*(1-10%) -> 1.251 | S4: ='Alaska Base'!$C$2*(1-14%) -> 1.1954 | T4: 0 | V4: ='SAF Supply'!A12 -> 2026 | W4: ='SAF Supply'!D12 -> 4.2608269e+08 | X4: ='SAF Supply'!E12 -> 3.4338245e+08 | Y4: ='SAF Supply'!L12 -> 4.2608269e+08 | Z4: ='SAF Supply'!M12 -> 32077747 | AB4: Required — 14% | AC4: =Outputs!B16*100 -> 9.0719939 | AE4: Net SAF premium | AF4: =Outputs!B27*100 -> 1.9676064
A5: Target SAF share | B5: =Outputs!B8 -> 0.1 | F5: SAF supply case | G5: =Inputs!B16 -> Base | K5: Projected revenue — 2030 | L5: =Outputs!B24 -> 1.5991017e+10 | P5: =Model!A4 -> 2027 | Q5: =Model!AB4 -> 1.2711038 | R5: ='Alaska Base'!$C$2*(1-10%) -> 1.251 | S5: ='Alaska Base'!$C$2*(1-14%) -> 1.1954 | T5: 0 | V5: ='SAF Supply'!A13 -> 2027 | W5: ='SAF Supply'!D13 -> 6.3096443e+08 | X5: ='SAF Supply'!E13 -> 4.0980126e+08 | Y5: ='SAF Supply'!L13 -> 6.3096443e+08 | Z5: ='SAF Supply'!M13 -> 53952468 | AB5: Target | AC5: =Outputs!B8*100 -> 10 | AE5: Catalytic Capital | AF5: =Inputs!B15*100 -> 0
A6: Effective SAF share | B6: =Outputs!B9 -> 0.1 | F6: U.S. SAF availability — 2030 | G6: =Outputs!B10 -> 2048980612 | K6: Net SAF premium / Revenue | L6: =Outputs!B27 -> 0.019676064 | P6: =Model!A5 -> 2028 | Q6: =Model!AB5 -> 1.2420647 | R6: ='Alaska Base'!$C$2*(1-10%) -> 1.251 | S6: ='Alaska Base'!$C$2*(1-14%) -> 1.1954 | T6: 0 | V6: ='SAF Supply'!A14 -> 2028 | W6: ='SAF Supply'!D14 -> 9.3436351e+08 | X6: ='SAF Supply'!E14 -> 4.8906713e+08 | Y6: ='SAF Supply'!L14 -> 9.3436351e+08 | Z6: ='SAF Supply'!M14 -> 76502795 | AB6: Effective | AC6: =Outputs!B9*100 -> 10
A7: Required SAF share — 14% | B7: =Outputs!B16 -> 0.090719939 | F7: DOE announced capacity ref. | G7: =Inputs!B29 -> 3000000000 | K7: Baseline aircraft capital / Revenue | L7: =Outputs!B28 -> 0.065661863 | P7: =Model!A6 -> 2029 | Q7: =Model!AB6 -> 1.2138018 | R7: ='Alaska Base'!$C$2*(1-10%) -> 1.251 | S7: ='Alaska Base'!$C$2*(1-14%) -> 1.1954 | T7: 0 | V7: ='SAF Supply'!A15 -> 2029 | W7: ='SAF Supply'!D15 -> 1.3836519e+09 | X7: ='SAF Supply'!E15 -> 5.8366503e+08 | Y7: ='SAF Supply'!L15 -> 1.3836519e+09 | Z7: ='SAF Supply'!M15 -> 99781096
A8: Modeled GHG intensity | B8: =Outputs!B21 -> 1.1858308 | F8: Alaska target SAF gallons | G8: =Outputs!B11 -> 1.2377986e+08 | K8: Catalytic Capital / Revenue | L8: =Inputs!B15 -> 0 | P8: =Model!A7 -> 2030 | Q8: =Model!AB7 -> 1.1858308 | R8: ='Alaska Base'!$C$2*(1-10%) -> 1.251 | S8: ='Alaska Base'!$C$2*(1-14%) -> 1.1954 | T8: 0 | V8: ='SAF Supply'!A16 -> 2030 | W8: ='SAF Supply'!D16 -> 2048980612 | X8: ='SAF Supply'!E16 -> 6.9656054e+08 | Y8: ='SAF Supply'!L16 -> 2048980612 | Z8: ='SAF Supply'!M16 -> 1.2377986e+08
A9: Reduction vs 2019 | B9: =Outputs!B22 -> 0.14688432 | F9: Market capture required | G9: =Outputs!B13 -> 0.060410457 | K9: Known capital + SAF + catalytic / Revenue | L9: =Outputs!B29 -> 0.085337927 | P9: =Model!A8 -> 2031 | Q9: =Model!AB8 -> 1.1254325 | R9: ='Alaska Base'!$C$2*(1-10%) -> 1.251 | S9: ='Alaska Base'!$C$2*(1-14%) -> 1.1954 | T9: 0 | V9: ='SAF Supply'!A17 -> 2031 | W9: ='SAF Supply'!D17 -> 2.1983125e+09 | X9: ='SAF Supply'!E17 -> 8.3129288e+08 | Y9: ='SAF Supply'!L17 -> 2.1983125e+09 | Z9: ='SAF Supply'!M17 -> 1.8861475e+08
A10: Target status | B10: =Outputs!B23 -> Meets 14% target | F10: SAF supply gap | G10: =Outputs!B14 -> 0 | K10: Partner share of SAF premium | L10: =Inputs!B10 -> 0 | P10: =Model!A9 -> 2032 | Q10: =Model!AB9 -> 1.0653608 | R10: ='Alaska Base'!$C$2*(1-10%) -> 1.251 | S10: ='Alaska Base'!$C$2*(1-14%) -> 1.1954 | T10: 0 | V10: ='SAF Supply'!A18 -> 2032 | W10: ='SAF Supply'!D18 -> 2.3585279e+09 | X10: ='SAF Supply'!E18 -> 9.9208585e+08 | Y10: ='SAF Supply'!L18 -> 2.3585279e+09 | Z10: ='SAF Supply'!M18 -> 2.5642229e+08
A11: Operational efficiency index | B11: =Outputs!B5 -> 1.0397556 | F11: Catalytic Capital / Revenue | G11: =Inputs!B15 -> 0 | K11: Net SAF premium — 2030 | L11: =Outputs!B25 -> 3.1464028e+08 | P11: =Model!A10 -> 2033 | Q11: =Model!AB10 -> 1.0061859 | R11: ='Alaska Base'!$C$2*(1-10%) -> 1.251 | S11: ='Alaska Base'!$C$2*(1-14%) -> 1.1954 | T11: 0 | V11: ='SAF Supply'!A19 -> 2033 | W11: ='SAF Supply'!D19 -> 2.5304199e+09 | X11: ='SAF Supply'!E19 -> 1.1839802e+09 | Y11: ='SAF Supply'!L19 -> 2.5304199e+09 | Z11: ='SAF Supply'!M19 -> 3.2681146e+08
P12: =Model!A11 -> 2034 | Q12: =Model!AB11 -> 0.94800968 | R12: ='Alaska Base'!$C$2*(1-10%) -> 1.251 | S12: ='Alaska Base'!$C$2*(1-14%) -> 1.1954 | T12: 0 | V12: ='SAF Supply'!A20 -> 2034 | W12: ='SAF Supply'!D20 -> 2.7148396e+09 | X12: ='SAF Supply'!E20 -> 1.4129918e+09 | Y12: ='SAF Supply'!L20 -> 2.7148396e+09 | Z12: ='SAF Supply'!M20 -> 3.9989888e+08
A13: 2040 Net-Zero Closure — Single Carbon Planning Price | P13: =Model!A12 -> 2035 | Q13: =Model!AB12 -> 0.89076594 | R13: ='Alaska Base'!$C$2*(1-10%) -> 1.251 | S13: ='Alaska Base'!$C$2*(1-14%) -> 1.1954 | T13: 0 | V13: ='SAF Supply'!A21 -> 2035 | W13: ='SAF Supply'!D21 -> 2912700000 | X13: ='SAF Supply'!E21 -> 1686300000 | Y13: ='SAF Supply'!L21 -> 2912700000 | Z13: ='SAF Supply'!M21 -> 4.7576185e+08
A14: Target SAF Share | B14: =Outputs!B37 -> 0.6 | F14: Carbon Planning Price | G14: =Outputs!B46 -> 200 | P14: =Model!A13 -> 2036 | Q14: =Model!AB13 -> 0.83444103 | R14: ='Alaska Base'!$C$2*(1-10%) -> 1.251 | S14: ='Alaska Base'!$C$2*(1-14%) -> 1.1954 | T14: 0 | V14: ='SAF Supply'!A22 -> 2036 | W14: ='SAF Supply'!D22 -> 3.20397e+09 | X14: ='SAF Supply'!E22 -> 1.85493e+09 | Y14: ='SAF Supply'!L22 -> 3.20397e+09 | Z14: ='SAF Supply'!M22 -> 5.5449534e+08
A15: Effective SAF Share | B15: =Outputs!B38 -> 0.6 | F15: Carbon Closure Cost | G15: =Outputs!B47 -> 1.4235973e+09 | P15: =Model!A14 -> 2037 | Q15: =Model!AB14 -> 0.77905984 | R15: ='Alaska Base'!$C$2*(1-10%) -> 1.251 | S15: ='Alaska Base'!$C$2*(1-14%) -> 1.1954 | T15: 0 | V15: ='SAF Supply'!A23 -> 2037 | W15: ='SAF Supply'!D23 -> 3.524367e+09 | X15: ='SAF Supply'!E23 -> 2.040423e+09 | Y15: ='SAF Supply'!L23 -> 3.524367e+09 | Z15: ='SAF Supply'!M23 -> 6.3439938e+08
A16: U.S. SAF Availability | B16: =Outputs!B39 -> 2912700000 | F16: Net SAF Premium | G16: =Outputs!B48 -> 2.6460623e+09 | P16: =Model!A15 -> 2038 | Q16: =Model!AB15 -> 0.72441963 | R16: ='Alaska Base'!$C$2*(1-10%) -> 1.251 | S16: ='Alaska Base'!$C$2*(1-14%) -> 1.1954 | T16: 0 | V16: ='SAF Supply'!A24 -> 2038 | W16: ='SAF Supply'!D24 -> 3.8768037e+09 | X16: ='SAF Supply'!E24 -> 2.2444653e+09 | Y16: ='SAF Supply'!L24 -> 3.8768037e+09 | Z16: ='SAF Supply'!M24 -> 7.1676465e+08
A17: Market Capture Required | B17: =Outputs!B40 -> 0.30540215 | F17: Corporate / Partner Contribution | G17: =Outputs!B49 -> 0 | P17: =Model!A16 -> 2039 | Q17: =Model!AB16 -> 0.67073083 | R17: ='Alaska Base'!$C$2*(1-10%) -> 1.251 | S17: ='Alaska Base'!$C$2*(1-14%) -> 1.1954 | T17: 0 | V17: ='SAF Supply'!A25 -> 2039 | W17: ='SAF Supply'!D25 -> 4.2644841e+09 | X17: ='SAF Supply'!E25 -> 2.4689118e+09 | Y17: ='SAF Supply'!L25 -> 4.2644841e+09 | Z17: ='SAF Supply'!M25 -> 8.0186041e+08
A18: Aircraft GHG Intensity | B18: =Outputs!B42 -> 0.61778289 | F18: Total Modeled Decarb Premium | G18: =Outputs!B50 -> 4.0696597e+09 | P18: =Model!A17 -> 2040 | Q18: =Model!AB17 -> 0.61778289 | R18: ='Alaska Base'!$C$2*(1-10%) -> 1.251 | S18: ='Alaska Base'!$C$2*(1-14%) -> 1.1954 | T18: 0 | V18: ='SAF Supply'!A26 -> 2040 | W18: ='SAF Supply'!D26 -> 4.6909325e+09 | X18: ='SAF Supply'!E26 -> 2.715803e+09 | Y18: ='SAF Supply'!L26 -> 4.6909325e+09 | Z18: ='SAF Supply'!M26 -> 8.8954484e+08
A19: Reduction vs 2019 | B19: =Outputs!B43 -> 0.55555187 | F19: Decarb Cost / Revenue | G19: =Outputs!B51 -> 0.19584523
A20: Operational Residual Emissions | B20: =Outputs!B45 -> 7117986.6 | F20: Remaining Gap After Carbon Closure | G20: =Outputs!B52 -> 0
A51: Simplified architecture: FAA activity and EIA efficiency drive physical operations. Projected revenue is 2025 Alaska revenue scaled by business activity; FAA yield is no longer used. All major financial burdens are normalized to projected revenue. Catalytic Capital is a % of revenue and only increases future SAF supply. Carbon closure uses one planning price ($200/t by default) rather than a dynamic CORSIA/removal blend. Carbon-market research remains documented in the assumptions sheets but is not part of the active pricing engine.

Sheet SAF Supply
A1: U.S. SAF Supply Outlook — Observed Actuals, Published Anchors, and Alaska Demand
A3: Year | B3: EPA Actual / YTD SAF (gal) | C3: Actual Status | D3: Probable / Base Production | E3: Conservative Production | F3: DOE Announced Capacity Ref. | G3: Selected Base Supply | H3: Projected Revenue | I3: Catalytic Capital Investment | J3: Matured Catalytic Capital | K3: Incremental SAF Capacity | L3: Adjusted U.S. SAF Availability | M3: Alaska Target SAF Gallons | N3: Alaska Effective SAF Gallons | O3: Market Capture Required | P3: Supply Gap | Q3: Source / Note | R3: Source URL
A4: 2018 | B4: =IF(A4<=2026,SUMIFS(EPA_SAF!$G$2:$G$2160,EPA_SAF!$A$2:$A$2160,A4,EPA_SAF!$H$2:$H$2160,1),"") -> 1828178 | C4: =IF(A4<2026,"Full year",IF(A4=2026,"YTD through latest EPA cut","")) -> Full year | D4: =IF(A4<2025,"",IF(A4=2025,B4,IF(A4<=2030,$B$11*(Inputs!$B$28/$B$11)^((A4-2025)/5),IF(A4<=2035,Inputs!$B$28*(Inputs!$B$30/Inputs!$B$28)^((A4-2030)/5),Inputs!$B$30*(1+Inputs!$B$17)^(A4-2035))))) | E4: =IF(A4<2025,"",IF(A4<=2035,$B$11*(Inputs!$B$31/$B$11)^((A4-2025)/10),Inputs!$B$31*(1+Inputs!$B$17)^(A4-2035))) | F4: =IF(A4=2030,Inputs!$B$29,"") | G4: =IF(Inputs!$B$16="Conservative",E4,D4) | H4: =IF(A4<2025,"",INDEX(Model!$Y$2:$Y$17,MATCH(A4,Model!$A$2:$A$17,0))) | I4: =IF(H4="","",H4*Inputs!$B$15) | J4: =IF(A4<2025+Inputs!$B$27,0,SUMIFS($I$4:$I$26,$A$4:$A$26,"<="&A4-Inputs!$B$27)) -> 0 | K4: =IF(G4="","",J4/Inputs!$B$26) | L4: =IF(G4="","",G4+K4) | M4: =IF(A4<2025,"",INDEX(Model!$K$2:$K$17,MATCH(A4,Model!$A$2:$A$17,0))) | N4: =IF(A4<2025,"",INDEX(Model!$P$2:$P$17,MATCH(A4,Model!$A$2:$A$17,0))) | O4: =IF(OR(L4="",L4=0),"",M4/L4) | P4: =IF(L4="","",MAX(0,M4-L4)) | Q4: EPA RFS-tracked renewable jet fuel volume | R4: https://www.epa.gov/fuels-registration-reporting-and-compliance-help/spreadsheet-rin-generation-and-renewable-fuel-0
A5: 2019 | B5: =IF(A5<=2026,SUMIFS(EPA_SAF!$G$2:$G$2160,EPA_SAF!$A$2:$A$2160,A5,EPA_SAF!$H$2:$H$2160,1),"") -> 2428702 | C5: =IF(A5<2026,"Full year",IF(A5=2026,"YTD through latest EPA cut","")) -> Full year | D5: =IF(A5<2025,"",IF(A5=2025,B5,IF(A5<=2030,$B$11*(Inputs!$B$28/$B$11)^((A5-2025)/5),IF(A5<=2035,Inputs!$B$28*(Inputs!$B$30/Inputs!$B$28)^((A5-2030)/5),Inputs!$B$30*(1+Inputs!$B$17)^(A5-2035))))) | E5: =IF(A5<2025,"",IF(A5<=2035,$B$11*(Inputs!$B$31/$B$11)^((A5-2025)/10),Inputs!$B$31*(1+Inputs!$B$17)^(A5-2035))) | F5: =IF(A5=2030,Inputs!$B$29,"") | G5: =IF(Inputs!$B$16="Conservative",E5,D5) | H5: =IF(A5<2025,"",INDEX(Model!$Y$2:$Y$17,MATCH(A5,Model!$A$2:$A$17,0))) | I5: =IF(H5="","",H5*Inputs!$B$15) | J5: =IF(A5<2025+Inputs!$B$27,0,SUMIFS($I$4:$I$26,$A$4:$A$26,"<="&A5-Inputs!$B$27)) -> 0 | K5: =IF(G5="","",J5/Inputs!$B$26) | L5: =IF(G5="","",G5+K5) | M5: =IF(A5<2025,"",INDEX(Model!$K$2:$K$17,MATCH(A5,Model!$A$2:$A$17,0))) | N5: =IF(A5<2025,"",INDEX(Model!$P$2:$P$17,MATCH(A5,Model!$A$2:$A$17,0))) | O5: =IF(OR(L5="",L5=0),"",M5/L5) | P5: =IF(L5="","",MAX(0,M5-L5)) | Q5: EPA RFS-tracked renewable jet fuel volume | R5: https://www.epa.gov/fuels-registration-reporting-and-compliance-help/spreadsheet-rin-generation-and-renewable-fuel-0
A6: 2020 | B6: =IF(A6<=2026,SUMIFS(EPA_SAF!$G$2:$G$2160,EPA_SAF!$A$2:$A$2160,A6,EPA_SAF!$H$2:$H$2160,1),"") -> 4608399 | C6: =IF(A6<2026,"Full year",IF(A6=2026,"YTD through latest EPA cut","")) -> Full year | D6: =IF(A6<2025,"",IF(A6=2025,B6,IF(A6<=2030,$B$11*(Inputs!$B$28/$B$11)^((A6-2025)/5),IF(A6<=2035,Inputs!$B$28*(Inputs!$B$30/Inputs!$B$28)^((A6-2030)/5),Inputs!$B$30*(1+Inputs!$B$17)^(A6-2035))))) | E6: =IF(A6<2025,"",IF(A6<=2035,$B$11*(Inputs!$B$31/$B$11)^((A6-2025)/10),Inputs!$B$31*(1+Inputs!$B$17)^(A6-2035))) | F6: =IF(A6=2030,Inputs!$B$29,"") | G6: =IF(Inputs!$B$16="Conservative",E6,D6) | H6: =IF(A6<2025,"",INDEX(Model!$Y$2:$Y$17,MATCH(A6,Model!$A$2:$A$17,0))) | I6: =IF(H6="","",H6*Inputs!$B$15) | J6: =IF(A6<2025+Inputs!$B$27,0,SUMIFS($I$4:$I$26,$A$4:$A$26,"<="&A6-Inputs!$B$27)) -> 0 | K6: =IF(G6="","",J6/Inputs!$B$26) | L6: =IF(G6="","",G6+K6) | M6: =IF(A6<2025,"",INDEX(Model!$K$2:$K$17,MATCH(A6,Model!$A$2:$A$17,0))) | N6: =IF(A6<2025,"",INDEX(Model!$P$2:$P$17,MATCH(A6,Model!$A$2:$A$17,0))) | O6: =IF(OR(L6="",L6=0),"",M6/L6) | P6: =IF(L6="","",MAX(0,M6-L6)) | Q6: EPA RFS-tracked renewable jet fuel volume | R6: https://www.epa.gov/fuels-registration-reporting-and-compliance-help/spreadsheet-rin-generation-and-renewable-fuel-0
A7: 2021 | B7: =IF(A7<=2026,SUMIFS(EPA_SAF!$G$2:$G$2160,EPA_SAF!$A$2:$A$2160,A7,EPA_SAF!$H$2:$H$2160,1),"") -> 5080073 | C7: =IF(A7<2026,"Full year",IF(A7=2026,"YTD through latest EPA cut","")) -> Full year | D7: =IF(A7<2025,"",IF(A7=2025,B7,IF(A7<=2030,$B$11*(Inputs!$B$28/$B$11)^((A7-2025)/5),IF(A7<=2035,Inputs!$B$28*(Inputs!$B$30/Inputs!$B$28)^((A7-2030)/5),Inputs!$B$30*(1+Inputs!$B$17)^(A7-2035))))) | E7: =IF(A7<2025,"",IF(A7<=2035,$B$11*(Inputs!$B$31/$B$11)^((A7-2025)/10),Inputs!$B$31*(1+Inputs!$B$17)^(A7-2035))) | F7: =IF(A7=2030,Inputs!$B$29,"") | G7: =IF(Inputs!$B$16="Conservative",E7,D7) | H7: =IF(A7<2025,"",INDEX(Model!$Y$2:$Y$17,MATCH(A7,Model!$A$2:$A$17,0))) | I7: =IF(H7="","",H7*Inputs!$B$15) | J7: =IF(A7<2025+Inputs!$B$27,0,SUMIFS($I$4:$I$26,$A$4:$A$26,"<="&A7-Inputs!$B$27)) -> 0 | K7: =IF(G7="","",J7/Inputs!$B$26) | L7: =IF(G7="","",G7+K7) | M7: =IF(A7<2025,"",INDEX(Model!$K$2:$K$17,MATCH(A7,Model!$A$2:$A$17,0))) | N7: =IF(A7<2025,"",INDEX(Model!$P$2:$P$17,MATCH(A7,Model!$A$2:$A$17,0))) | O7: =IF(OR(L7="",L7=0),"",M7/L7) | P7: =IF(L7="","",MAX(0,M7-L7)) | Q7: EPA RFS-tracked renewable jet fuel volume | R7: https://www.epa.gov/fuels-registration-reporting-and-compliance-help/spreadsheet-rin-generation-and-renewable-fuel-0
A8: 2022 | B8: =IF(A8<=2026,SUMIFS(EPA_SAF!$G$2:$G$2160,EPA_SAF!$A$2:$A$2160,A8,EPA_SAF!$H$2:$H$2160,1),"") -> 15819877 | C8: =IF(A8<2026,"Full year",IF(A8=2026,"YTD through latest EPA cut","")) -> Full year | D8: =IF(A8<2025,"",IF(A8=2025,B8,IF(A8<=2030,$B$11*(Inputs!$B$28/$B$11)^((A8-2025)/5),IF(A8<=2035,Inputs!$B$28*(Inputs!$B$30/Inputs!$B$28)^((A8-2030)/5),Inputs!$B$30*(1+Inputs!$B$17)^(A8-2035))))) | E8: =IF(A8<2025,"",IF(A8<=2035,$B$11*(Inputs!$B$31/$B$11)^((A8-2025)/10),Inputs!$B$31*(1+Inputs!$B$17)^(A8-2035))) | F8: =IF(A8=2030,Inputs!$B$29,"") | G8: =IF(Inputs!$B$16="Conservative",E8,D8) | H8: =IF(A8<2025,"",INDEX(Model!$Y$2:$Y$17,MATCH(A8,Model!$A$2:$A$17,0))) | I8: =IF(H8="","",H8*Inputs!$B$15) | J8: =IF(A8<2025+Inputs!$B$27,0,SUMIFS($I$4:$I$26,$A$4:$A$26,"<="&A8-Inputs!$B$27)) -> 0 | K8: =IF(G8="","",J8/Inputs!$B$26) | L8: =IF(G8="","",G8+K8) | M8: =IF(A8<2025,"",INDEX(Model!$K$2:$K$17,MATCH(A8,Model!$A$2:$A$17,0))) | N8: =IF(A8<2025,"",INDEX(Model!$P$2:$P$17,MATCH(A8,Model!$A$2:$A$17,0))) | O8: =IF(OR(L8="",L8=0),"",M8/L8) | P8: =IF(L8="","",MAX(0,M8-L8)) | Q8: EPA RFS-tracked renewable jet fuel volume | R8: https://www.epa.gov/fuels-registration-reporting-and-compliance-help/spreadsheet-rin-generation-and-renewable-fuel-0
A9: 2023 | B9: =IF(A9<=2026,SUMIFS(EPA_SAF!$G$2:$G$2160,EPA_SAF!$A$2:$A$2160,A9,EPA_SAF!$H$2:$H$2160,1),"") -> 26300097 | C9: =IF(A9<2026,"Full year",IF(A9=2026,"YTD through latest EPA cut","")) -> Full year | D9: =IF(A9<2025,"",IF(A9=2025,B9,IF(A9<=2030,$B$11*(Inputs!$B$28/$B$11)^((A9-2025)/5),IF(A9<=2035,Inputs!$B$28*(Inputs!$B$30/Inputs!$B$28)^((A9-2030)/5),Inputs!$B$30*(1+Inputs!$B$17)^(A9-2035))))) | E9: =IF(A9<2025,"",IF(A9<=2035,$B$11*(Inputs!$B$31/$B$11)^((A9-2025)/10),Inputs!$B$31*(1+Inputs!$B$17)^(A9-2035))) | F9: =IF(A9=2030,Inputs!$B$29,"") | G9: =IF(Inputs!$B$16="Conservative",E9,D9) | H9: =IF(A9<2025,"",INDEX(Model!$Y$2:$Y$17,MATCH(A9,Model!$A$2:$A$17,0))) | I9: =IF(H9="","",H9*Inputs!$B$15) | J9: =IF(A9<2025+Inputs!$B$27,0,SUMIFS($I$4:$I$26,$A$4:$A$26,"<="&A9-Inputs!$B$27)) -> 0 | K9: =IF(G9="","",J9/Inputs!$B$26) | L9: =IF(G9="","",G9+K9) | M9: =IF(A9<2025,"",INDEX(Model!$K$2:$K$17,MATCH(A9,Model!$A$2:$A$17,0))) | N9: =IF(A9<2025,"",INDEX(Model!$P$2:$P$17,MATCH(A9,Model!$A$2:$A$17,0))) | O9: =IF(OR(L9="",L9=0),"",M9/L9) | P9: =IF(L9="","",MAX(0,M9-L9)) | Q9: EPA RFS-tracked renewable jet fuel volume | R9: https://www.epa.gov/fuels-registration-reporting-and-compliance-help/spreadsheet-rin-generation-and-renewable-fuel-0
A10: 2024 | B10: =IF(A10<=2026,SUMIFS(EPA_SAF!$G$2:$G$2160,EPA_SAF!$A$2:$A$2160,A10,EPA_SAF!$H$2:$H$2160,1),"") -> 111864983 | C10: =IF(A10<2026,"Full year",IF(A10=2026,"YTD through latest EPA cut","")) -> Full year | D10: =IF(A10<2025,"",IF(A10=2025,B10,IF(A10<=2030,$B$11*(Inputs!$B$28/$B$11)^((A10-2025)/5),IF(A10<=2035,Inputs!$B$28*(Inputs!$B$30/Inputs!$B$28)^((A10-2030)/5),Inputs!$B$30*(1+Inputs!$B$17)^(A10-2035))))) | E10: =IF(A10<2025,"",IF(A10<=2035,$B$11*(Inputs!$B$31/$B$11)^((A10-2025)/10),Inputs!$B$31*(1+Inputs!$B$17)^(A10-2035))) | F10: =IF(A10=2030,Inputs!$B$29,"") | G10: =IF(Inputs!$B$16="Conservative",E10,D10) | H10: =IF(A10<2025,"",INDEX(Model!$Y$2:$Y$17,MATCH(A10,Model!$A$2:$A$17,0))) | I10: =IF(H10="","",H10*Inputs!$B$15) | J10: =IF(A10<2025+Inputs!$B$27,0,SUMIFS($I$4:$I$26,$A$4:$A$26,"<="&A10-Inputs!$B$27)) -> 0 | K10: =IF(G10="","",J10/Inputs!$B$26) | L10: =IF(G10="","",G10+K10) | M10: =IF(A10<2025,"",INDEX(Model!$K$2:$K$17,MATCH(A10,Model!$A$2:$A$17,0))) | N10: =IF(A10<2025,"",INDEX(Model!$P$2:$P$17,MATCH(A10,Model!$A$2:$A$17,0))) | O10: =IF(OR(L10="",L10=0),"",M10/L10) | P10: =IF(L10="","",MAX(0,M10-L10)) | Q10: EPA RFS-tracked renewable jet fuel volume | R10: https://www.epa.gov/fuels-registration-reporting-and-compliance-help/spreadsheet-rin-generation-and-renewable-fuel-0
A11: 2025 | B11: =IF(A11<=2026,SUMIFS(EPA_SAF!$G$2:$G$2160,EPA_SAF!$A$2:$A$2160,A11,EPA_SAF!$H$2:$H$2160,1),"") -> 287728509 | C11: =IF(A11<2026,"Full year",IF(A11=2026,"YTD through latest EPA cut","")) -> Full year | D11: =IF(A11<2025,"",IF(A11=2025,B11,IF(A11<=2030,$B$11*(Inputs!$B$28/$B$11)^((A11-2025)/5),IF(A11<=2035,Inputs!$B$28*(Inputs!$B$30/Inputs!$B$28)^((A11-2030)/5),Inputs!$B$30*(1+Inputs!$B$17)^(A11-2035))))) -> 287728509 | E11: =IF(A11<2025,"",IF(A11<=2035,$B$11*(Inputs!$B$31/$B$11)^((A11-2025)/10),Inputs!$B$31*(1+Inputs!$B$17)^(A11-2035))) -> 287728509 | F11: =IF(A11=2030,Inputs!$B$29,"") | G11: =IF(Inputs!$B$16="Conservative",E11,D11) -> 287728509 | H11: =IF(A11<2025,"",INDEX(Model!$Y$2:$Y$17,MATCH(A11,Model!$A$2:$A$17,0))) -> 14239000000 | I11: =IF(H11="","",H11*Inputs!$B$15) -> 0 | J11: =IF(A11<2025+Inputs!$B$27,0,SUMIFS($I$4:$I$26,$A$4:$A$26,"<="&A11-Inputs!$B$27)) -> 0 | K11: =IF(G11="","",J11/Inputs!$B$26) -> 0 | L11: =IF(G11="","",G11+K11) -> 287728509 | M11: =IF(A11<2025,"",INDEX(Model!$K$2:$K$17,MATCH(A11,Model!$A$2:$A$17,0))) -> 10891144 | N11: =IF(A11<2025,"",INDEX(Model!$P$2:$P$17,MATCH(A11,Model!$A$2:$A$17,0))) -> 10891144 | O11: =IF(OR(L11="",L11=0),"",M11/L11) -> 0.037852155 | P11: =IF(L11="","",MAX(0,M11-L11)) -> 0 | Q11: EPA full-year actual; common starting point for forward supply scenarios | R11: https://www.epa.gov/fuels-registration-reporting-and-compliance-help/spreadsheet-rin-generation-and-renewable-fuel-0
A12: 2026 | B12: =IF(A12<=2026,SUMIFS(EPA_SAF!$G$2:$G$2160,EPA_SAF!$A$2:$A$2160,A12,EPA_SAF!$H$2:$H$2160,1),"") -> 182960877 | C12: =IF(A12<2026,"Full year",IF(A12=2026,"YTD through latest EPA cut","")) -> YTD through latest EPA cut | D12: =IF(A12<2025,"",IF(A12=2025,B12,IF(A12<=2030,$B$11*(Inputs!$B$28/$B$11)^((A12-2025)/5),IF(A12<=2035,Inputs!$B$28*(Inputs!$B$30/Inputs!$B$28)^((A12-2030)/5),Inputs!$B$30*(1+Inputs!$B$17)^(A12-2035))))) -> 4.2608269e+08 | E12: =IF(A12<2025,"",IF(A12<=2035,$B$11*(Inputs!$B$31/$B$11)^((A12-2025)/10),Inputs!$B$31*(1+Inputs!$B$17)^(A12-2035))) -> 3.4338245e+08 | F12: =IF(A12=2030,Inputs!$B$29,"") | G12: =IF(Inputs!$B$16="Conservative",E12,D12) -> 4.2608269e+08 | H12: =IF(A12<2025,"",INDEX(Model!$Y$2:$Y$17,MATCH(A12,Model!$A$2:$A$17,0))) -> 1.4552776e+10 | I12: =IF(H12="","",H12*Inputs!$B$15) -> 0 | J12: =IF(A12<2025+Inputs!$B$27,0,SUMIFS($I$4:$I$26,$A$4:$A$26,"<="&A12-Inputs!$B$27)) -> 0 | K12: =IF(G12="","",J12/Inputs!$B$26) -> 0 | L12: =IF(G12="","",G12+K12) -> 4.2608269e+08 | M12: =IF(A12<2025,"",INDEX(Model!$K$2:$K$17,MATCH(A12,Model!$A$2:$A$17,0))) -> 32077747 | N12: =IF(A12<2025,"",INDEX(Model!$P$2:$P$17,MATCH(A12,Model!$A$2:$A$17,0))) -> 32077747 | O12: =IF(OR(L12="",L12=0),"",M12/L12) -> 0.075285263 | P12: =IF(L12="","",MAX(0,M12-L12)) -> 0 | Q12: EPA YTD actual shown separately; forward scenarios are not annualized from partial-year data | R12: https://www.epa.gov/fuels-registration-reporting-and-compliance-help/spreadsheet-rin-generation-and-renewable-fuel-0
A13: 2027 | B13: =IF(A13<=2026,SUMIFS(EPA_SAF!$G$2:$G$2160,EPA_SAF!$A$2:$A$2160,A13,EPA_SAF!$H$2:$H$2160,1),"") | C13: =IF(A13<2026,"Full year",IF(A13=2026,"YTD through latest EPA cut","")) | D13: =IF(A13<2025,"",IF(A13=2025,B13,IF(A13<=2030,$B$11*(Inputs!$B$28/$B$11)^((A13-2025)/5),IF(A13<=2035,Inputs!$B$28*(Inputs!$B$30/Inputs!$B$28)^((A13-2030)/5),Inputs!$B$30*(1+Inputs!$B$17)^(A13-2035))))) -> 6.3096443e+08 | E13: =IF(A13<2025,"",IF(A13<=2035,$B$11*(Inputs!$B$31/$B$11)^((A13-2025)/10),Inputs!$B$31*(1+Inputs!$B$17)^(A13-2035))) -> 4.0980126e+08 | F13: =IF(A13=2030,Inputs!$B$29,"") | G13: =IF(Inputs!$B$16="Conservative",E13,D13) -> 6.3096443e+08 | H13: =IF(A13<2025,"",INDEX(Model!$Y$2:$Y$17,MATCH(A13,Model!$A$2:$A$17,0))) -> 1.489973e+10 | I13: =IF(H13="","",H13*Inputs!$B$15) -> 0 | J13: =IF(A13<2025+Inputs!$B$27,0,SUMIFS($I$4:$I$26,$A$4:$A$26,"<="&A13-Inputs!$B$27)) -> 0 | K13: =IF(G13="","",J13/Inputs!$B$26) -> 0 | L13: =IF(G13="","",G13+K13) -> 6.3096443e+08 | M13: =IF(A13<2025,"",INDEX(Model!$K$2:$K$17,MATCH(A13,Model!$A$2:$A$17,0))) -> 53952468 | N13: =IF(A13<2025,"",INDEX(Model!$P$2:$P$17,MATCH(A13,Model!$A$2:$A$17,0))) -> 53952468 | O13: =IF(OR(L13="",L13=0),"",M13/L13) -> 0.08550794 | P13: =IF(L13="","",MAX(0,M13-L13)) -> 0 | Q13: Base path heads to the peer-reviewed 2030 probable-production anchor; conservative path independently compounds toward the 2035 Rystad low case | R13: https://www.sciencedirect.com/science/article/pii/S0961953425009274
A14: 2028 | B14: =IF(A14<=2026,SUMIFS(EPA_SAF!$G$2:$G$2160,EPA_SAF!$A$2:$A$2160,A14,EPA_SAF!$H$2:$H$2160,1),"") | C14: =IF(A14<2026,"Full year",IF(A14=2026,"YTD through latest EPA cut","")) | D14: =IF(A14<2025,"",IF(A14=2025,B14,IF(A14<=2030,$B$11*(Inputs!$B$28/$B$11)^((A14-2025)/5),IF(A14<=2035,Inputs!$B$28*(Inputs!$B$30/Inputs!$B$28)^((A14-2030)/5),Inputs!$B$30*(1+Inputs!$B$17)^(A14-2035))))) -> 9.3436351e+08 | E14: =IF(A14<2025,"",IF(A14<=2035,$B$11*(Inputs!$B$31/$B$11)^((A14-2025)/10),Inputs!$B$31*(1+Inputs!$B$17)^(A14-2035))) -> 4.8906713e+08 | F14: =IF(A14=2030,Inputs!$B$29,"") | G14: =IF(Inputs!$B$16="Conservative",E14,D14) -> 9.3436351e+08 | H14: =IF(A14<2025,"",INDEX(Model!$Y$2:$Y$17,MATCH(A14,Model!$A$2:$A$17,0))) -> 1.5254956e+10 | I14: =IF(H14="","",H14*Inputs!$B$15) -> 0 | J14: =IF(A14<2025+Inputs!$B$27,0,SUMIFS($I$4:$I$26,$A$4:$A$26,"<="&A14-Inputs!$B$27)) -> 0 | K14: =IF(G14="","",J14/Inputs!$B$26) -> 0 | L14: =IF(G14="","",G14+K14) -> 9.3436351e+08 | M14: =IF(A14<2025,"",INDEX(Model!$K$2:$K$17,MATCH(A14,Model!$A$2:$A$17,0))) -> 76502795 | N14: =IF(A14<2025,"",INDEX(Model!$P$2:$P$17,MATCH(A14,Model!$A$2:$A$17,0))) -> 76502795 | O14: =IF(OR(L14="",L14=0),"",M14/L14) -> 0.081876908 | P14: =IF(L14="","",MAX(0,M14-L14)) -> 0 | Q14: Base path heads to the peer-reviewed 2030 probable-production anchor; conservative path independently compounds toward the 2035 Rystad low case | R14: https://www.sciencedirect.com/science/article/pii/S0961953425009274
A15: 2029 | B15: =IF(A15<=2026,SUMIFS(EPA_SAF!$G$2:$G$2160,EPA_SAF!$A$2:$A$2160,A15,EPA_SAF!$H$2:$H$2160,1),"") | C15: =IF(A15<2026,"Full year",IF(A15=2026,"YTD through latest EPA cut","")) | D15: =IF(A15<2025,"",IF(A15=2025,B15,IF(A15<=2030,$B$11*(Inputs!$B$28/$B$11)^((A15-2025)/5),IF(A15<=2035,Inputs!$B$28*(Inputs!$B$30/Inputs!$B$28)^((A15-2030)/5),Inputs!$B$30*(1+Inputs!$B$17)^(A15-2035))))) -> 1.3836519e+09 | E15: =IF(A15<2025,"",IF(A15<=2035,$B$11*(Inputs!$B$31/$B$11)^((A15-2025)/10),Inputs!$B$31*(1+Inputs!$B$17)^(A15-2035))) -> 5.8366503e+08 | F15: =IF(A15=2030,Inputs!$B$29,"") | G15: =IF(Inputs!$B$16="Conservative",E15,D15) -> 1.3836519e+09 | H15: =IF(A15<2025,"",INDEX(Model!$Y$2:$Y$17,MATCH(A15,Model!$A$2:$A$17,0))) -> 1.5618651e+10 | I15: =IF(H15="","",H15*Inputs!$B$15) -> 0 | J15: =IF(A15<2025+Inputs!$B$27,0,SUMIFS($I$4:$I$26,$A$4:$A$26,"<="&A15-Inputs!$B$27)) -> 0 | K15: =IF(G15="","",J15/Inputs!$B$26) -> 0 | L15: =IF(G15="","",G15+K15) -> 1.3836519e+09 | M15: =IF(A15<2025,"",INDEX(Model!$K$2:$K$17,MATCH(A15,Model!$A$2:$A$17,0))) -> 99781096 | N15: =IF(A15<2025,"",INDEX(Model!$P$2:$P$17,MATCH(A15,Model!$A$2:$A$17,0))) -> 99781096 | O15: =IF(OR(L15="",L15=0),"",M15/L15) -> 0.072114303 | P15: =IF(L15="","",MAX(0,M15-L15)) -> 0 | Q15: Base path heads to the peer-reviewed 2030 probable-production anchor; conservative path independently compounds toward the 2035 Rystad low case | R15: https://www.sciencedirect.com/science/article/pii/S0961953425009274
... A26: 2040 | B26: =IF(A26<=2026,SUMIFS(EPA_SAF!$G$2:$G$2160,EPA_SAF!$A$2:$A$2160,A26,EPA_SAF!$H$2:$H$2160,1),"") | C26: =IF(A26<2026,"Full year",IF(A26=2026,"YTD through latest EPA cut","")) | D26: =IF(A26<2025,"",IF(A26=2025,B26,IF(A26<=2030,$B$11*(Inputs!$B$28/$B$11)^((A26-2025)/5),IF(A26<=2035,Inputs!$B$28*(Inputs!$B$30/Inputs!$B$28)^((A26-2030)/5),Inputs!$B$30*(1+Inputs!$B$17)^(A26-2035))))) -> 4.6909325e+09 | E26: =IF(A26<2025,"",IF(A26<=2035,$B$11*(Inputs!$B$31/$B$11)^((A26-2025)/10),Inputs!$B$31*(1+Inputs!$B$17)^(A26-2035))) -> 2.715803e+09 | F26: =IF(A26=2030,Inputs!$B$29,"") | G26: =IF(Inputs!$B$16="Conservative",E26,D26) -> 4.6909325e+09 | H26: =IF(A26<2025,"",INDEX(Model!$Y$2:$Y$17,MATCH(A26,Model!$A$2:$A$17,0))) -> 2.0779978e+10 | I26: =IF(H26="","",H26*Inputs!$B$15) -> 0 | J26: =IF(A26<2025+Inputs!$B$27,0,SUMIFS($I$4:$I$26,$A$4:$A$26,"<="&A26-Inputs!$B$27)) -> 0 | K26: =IF(G26="","",J26/Inputs!$B$26) -> 0 | L26: =IF(G26="","",G26+K26) -> 4.6909325e+09 | M26: =IF(A26<2025,"",INDEX(Model!$K$2:$K$17,MATCH(A26,Model!$A$2:$A$17,0))) -> 8.8954484e+08 | N26: =IF(A26<2025,"",INDEX(Model!$P$2:$P$17,MATCH(A26,Model!$A$2:$A$17,0))) -> 8.8954484e+08 | O26: =IF(OR(L26="",L26=0),"",M26/L26) -> 0.18963071 | P26: =IF(L26="","",MAX(0,M26-L26)) -> 0 | Q26: Post-2035 supply uses explicit user growth; default 0% holds the 2035 endpoint flat | R26: Model scenario after published 2035 anchor

Sheet Capital Allocation
A1: Capital Allocation Context — All Key Burdens as Share of Revenue
A3: Year | B3: Projected Revenue | C3: Baseline Fleet / Aircraft Capital | D3: Capital Basis | E3: Baseline Capital / Revenue | F3: Net SAF Premium | G3: SAF Premium / Revenue | H3: Catalytic Capital % of Revenue | I3: Catalytic Investment | J3: Known Capital + SAF + Catalytic / Revenue | K3: Source / Note | L3: Source URL
A4: 2025 | B4: =INDEX(Model!$Y$2:$Y$17,MATCH(A4,Model!$A$2:$A$17,0)) -> 14239000000 | C4: ='Alaska Base'!$C$27 -> 1600000000 | D4: Total capex actual | E4: =C4/B4 -> 0.11236744 | F4: =INDEX(Model!$W$2:$W$17,MATCH(A4,Model!$A$2:$A$17,0)) -> 27336771 | G4: =F4/B4 -> 0.0019198519 | H4: =Inputs!$B$15 -> 0 | I4: =B4*H4 -> 0 | J4: =(C4+F4+I4)/B4 -> 0.11428729 | K4: 2025 10-K | L4: https://www.sec.gov/Archives/edgar/data/766421/000076642126000010/alk-20251231.htm
A5: 2026 | B5: =INDEX(Model!$Y$2:$Y$17,MATCH(A5,Model!$A$2:$A$17,0)) -> 1.4552776e+10 | C5: ='Alaska Base'!$C$28 -> 1450000000 | D5: Total capex plan midpoint | E5: =C5/B5 -> 0.099637349 | F5: =INDEX(Model!$W$2:$W$17,MATCH(A5,Model!$A$2:$A$17,0)) -> 71806920 | G5: =F5/B5 -> 0.0049342422 | H5: =Inputs!$B$15 -> 0 | I5: =B5*H5 -> 0 | J5: =(C5+F5+I5)/B5 -> 0.10457159 | K5: 2026 Q1 10-Q guidance | L5: https://www.sec.gov/Archives/edgar/data/766421/000076642126000021/alk-20260331.htm
A6: 2027 | B6: =INDEX(Model!$Y$2:$Y$17,MATCH(A6,Model!$A$2:$A$17,0)) -> 1.489973e+10 | C6: =1614000000 -> 1614000000 | D6: Aircraft contractual commitments | E6: =C6/B6 -> 0.10832411 | F6: =INDEX(Model!$W$2:$W$17,MATCH(A6,Model!$A$2:$A$17,0)) -> 1.2953326e+08 | G6: =F6/B6 -> 0.0086936647 | H6: =Inputs!$B$15 -> 0 | I6: =B6*H6 -> 0 | J6: =(C6+F6+I6)/B6 -> 0.11701777 | K6: 2026 Q2 10-Q | L6: https://www.sec.gov/Archives/edgar/data/766421/000076642126000041/alk-20260630.htm
A7: 2028 | B7: =INDEX(Model!$Y$2:$Y$17,MATCH(A7,Model!$A$2:$A$17,0)) -> 1.5254956e+10 | C7: =1666000000 -> 1666000000 | D7: Aircraft contractual commitments | E7: =C7/B7 -> 0.10921041 | F7: =INDEX(Model!$W$2:$W$17,MATCH(A7,Model!$A$2:$A$17,0)) -> 1.8890269e+08 | G7: =F7/B7 -> 0.012383037 | H7: =Inputs!$B$15 -> 0 | I7: =B7*H7 -> 0 | J7: =(C7+F7+I7)/B7 -> 0.12159344 | K7: 2026 Q2 10-Q | L7: https://www.sec.gov/Archives/edgar/data/766421/000076642126000041/alk-20260630.htm
A8: 2029 | B8: =INDEX(Model!$Y$2:$Y$17,MATCH(A8,Model!$A$2:$A$17,0)) -> 1.5618651e+10 | C8: =1168000000 -> 1168000000 | D8: Aircraft contractual commitments | E8: =C8/B8 -> 0.074782385 | F8: =INDEX(Model!$W$2:$W$17,MATCH(A8,Model!$A$2:$A$17,0)) -> 2.5233325e+08 | G8: =F8/B8 -> 0.016155892 | H8: =Inputs!$B$15 -> 0 | I8: =B8*H8 -> 0 | J8: =(C8+F8+I8)/B8 -> 0.090938277 | K8: 2026 Q2 10-Q | L8: https://www.sec.gov/Archives/edgar/data/766421/000076642126000041/alk-20260630.htm
A9: 2030 | B9: =INDEX(Model!$Y$2:$Y$17,MATCH(A9,Model!$A$2:$A$17,0)) -> 1.5991017e+10 | C9: =1050000000 -> 1050000000 | D9: Aircraft contractual commitments | E9: =C9/B9 -> 0.065661863 | F9: =INDEX(Model!$W$2:$W$17,MATCH(A9,Model!$A$2:$A$17,0)) -> 3.1464028e+08 | G9: =F9/B9 -> 0.019676064 | H9: =Inputs!$B$15 -> 0 | I9: =B9*H9 -> 0 | J9: =(C9+F9+I9)/B9 -> 0.085337927 | K9: 2026 Q2 10-Q | L9: https://www.sec.gov/Archives/edgar/data/766421/000076642126000041/alk-20260630.htm
A11: 2031–2035 | C11: ='Alaska Base'!$C$29 -> 4264000000 | D11: Aggregate aircraft commitments | K11: 2026 Q2 10-Q; aggregate aircraft commitments shown in Alaska Base | L11: https://www.sec.gov/Archives/edgar/data/766421/000076642126000041/alk-20260630.htm

Sheet FAA Forecast
A1: FAA Baseline — System Activity, Nominal Yield, and Real Yield
A3: Year | B3: System ASMs (bn) | C3: Activity Index (2025=1) | D3: System Nominal Yield (¢/RPM) | E3: FAA CPI Index | F3: Real Yield Index (2025=1) | G3: Source / Note | H3: Published FAA anchors
A4: 2025 | B4: =IF(A4=2025,1375,IF(A4<=2026,1375*(1405.3/1375)^((A4-2025)/(2026-2025)),IF(A4<=2031,1405.3*(1581/1405.3)^((A4-2026)/(2031-2026)),IF(A4<=2036,1581*(1816.5/1581)^((A4-2031)/(2036-2031)),IF(A4<=2041,1816.5*(2057.2/1816.5)^((A4-2036)/(2041-2036)),2057.2*(2315/2057.2)^((A4-2041)/(2046-2041))))))) -> 1375 | C4: =B4/$B$4 -> 1 | D4: =IF(A4=2025,16.19,IF(A4<=2026,16.19*(16.36/16.19)^((A4-2025)/(2026-2025)),IF(A4<=2031,16.36*(17.98/16.36)^((A4-2026)/(2031-2026)),IF(A4<=2036,17.98*(19.73/17.98)^((A4-2031)/(2036-2031)),IF(A4<=2041,19.73*(21.27/19.73)^((A4-2036)/(2041-2036)),21.27*(22.97/21.27)^((A4-2041)/(2046-2041))))))) -> 16.19 | E4: =IF(A4=2025,3,IF(A4<=2026,3*(3.08/3)^((A4-2025)/(2026-2025)),IF(A4<=2031,3.08*(3.46/3.08)^((A4-2026)/(2031-2026)),IF(A4<=2036,3.46*(3.9/3.46)^((A4-2031)/(2036-2031)),IF(A4<=2041,3.9*(4.34/3.9)^((A4-2036)/(2041-2036)),4.34*(4.84/4.34)^((A4-2041)/(2046-2041))))))) -> 3 | F4: =(D4/E4)/($D$4/$E$4) -> 1 | G4: FAA Table A-2 baseline; annual values geometrically interpolated between published anchor years | H4: 2025: ASM 1,375.0; yield 16.19; CPI 3.00
A5: 2026 | B5: =IF(A5=2025,1375,IF(A5<=2026,1375*(1405.3/1375)^((A5-2025)/(2026-2025)),IF(A5<=2031,1405.3*(1581/1405.3)^((A5-2026)/(2031-2026)),IF(A5<=2036,1581*(1816.5/1581)^((A5-2031)/(2036-2031)),IF(A5<=2041,1816.5*(2057.2/1816.5)^((A5-2036)/(2041-2036)),2057.2*(2315/2057.2)^((A5-2041)/(2046-2041))))))) -> 1405.3 | C5: =B5/$B$4 -> 1.0220364 | D5: =IF(A5=2025,16.19,IF(A5<=2026,16.19*(16.36/16.19)^((A5-2025)/(2026-2025)),IF(A5<=2031,16.36*(17.98/16.36)^((A5-2026)/(2031-2026)),IF(A5<=2036,17.98*(19.73/17.98)^((A5-2031)/(2036-2031)),IF(A5<=2041,19.73*(21.27/19.73)^((A5-2036)/(2041-2036)),21.27*(22.97/21.27)^((A5-2041)/(2046-2041))))))) -> 16.36 | E5: =IF(A5=2025,3,IF(A5<=2026,3*(3.08/3)^((A5-2025)/(2026-2025)),IF(A5<=2031,3.08*(3.46/3.08)^((A5-2026)/(2031-2026)),IF(A5<=2036,3.46*(3.9/3.46)^((A5-2031)/(2036-2031)),IF(A5<=2041,3.9*(4.34/3.9)^((A5-2036)/(2041-2036)),4.34*(4.84/4.34)^((A5-2041)/(2046-2041))))))) -> 3.08 | F5: =(D5/E5)/($D$4/$E$4) -> 0.98425355 | G5: FAA Table A-2 baseline; annual values geometrically interpolated between published anchor years | H5: 2026: ASM 1,405.3; yield 16.36; CPI 3.08
A6: 2027 | B6: =IF(A6=2025,1375,IF(A6<=2026,1375*(1405.3/1375)^((A6-2025)/(2026-2025)),IF(A6<=2031,1405.3*(1581/1405.3)^((A6-2026)/(2031-2026)),IF(A6<=2036,1581*(1816.5/1581)^((A6-2031)/(2036-2031)),IF(A6<=2041,1816.5*(2057.2/1816.5)^((A6-2036)/(2041-2036)),2057.2*(2315/2057.2)^((A6-2041)/(2046-2041))))))) -> 1438.8039 | C6: =B6/$B$4 -> 1.0464028 | D6: =IF(A6=2025,16.19,IF(A6<=2026,16.19*(16.36/16.19)^((A6-2025)/(2026-2025)),IF(A6<=2031,16.36*(17.98/16.36)^((A6-2026)/(2031-2026)),IF(A6<=2036,17.98*(19.73/17.98)^((A6-2031)/(2036-2031)),IF(A6<=2041,19.73*(21.27/19.73)^((A6-2036)/(2041-2036)),21.27*(22.97/21.27)^((A6-2041)/(2046-2041))))))) -> 16.67188 | E6: =IF(A6=2025,3,IF(A6<=2026,3*(3.08/3)^((A6-2025)/(2026-2025)),IF(A6<=2031,3.08*(3.46/3.08)^((A6-2026)/(2031-2026)),IF(A6<=2036,3.46*(3.9/3.46)^((A6-2031)/(2036-2031)),IF(A6<=2041,3.9*(4.34/3.9)^((A6-2036)/(2041-2036)),4.34*(4.84/4.34)^((A6-2041)/(2046-2041))))))) -> 3.1525051 | F6: =(D6/E6)/($D$4/$E$4) -> 0.97994836 | G6: FAA Table A-2 baseline; annual values geometrically interpolated between published anchor years | H6: 2031: ASM 1,581.0; yield 17.98; CPI 3.46
A7: 2028 | B7: =IF(A7=2025,1375,IF(A7<=2026,1375*(1405.3/1375)^((A7-2025)/(2026-2025)),IF(A7<=2031,1405.3*(1581/1405.3)^((A7-2026)/(2031-2026)),IF(A7<=2036,1581*(1816.5/1581)^((A7-2031)/(2036-2031)),IF(A7<=2041,1816.5*(2057.2/1816.5)^((A7-2036)/(2041-2036)),2057.2*(2315/2057.2)^((A7-2041)/(2046-2041))))))) -> 1473.1066 | C7: =B7/$B$4 -> 1.0713503 | D7: =IF(A7=2025,16.19,IF(A7<=2026,16.19*(16.36/16.19)^((A7-2025)/(2026-2025)),IF(A7<=2031,16.36*(17.98/16.36)^((A7-2026)/(2031-2026)),IF(A7<=2036,17.98*(19.73/17.98)^((A7-2031)/(2036-2031)),IF(A7<=2041,19.73*(21.27/19.73)^((A7-2036)/(2041-2036)),21.27*(22.97/21.27)^((A7-2041)/(2046-2041))))))) -> 16.989706 | E7: =IF(A7=2025,3,IF(A7<=2026,3*(3.08/3)^((A7-2025)/(2026-2025)),IF(A7<=2031,3.08*(3.46/3.08)^((A7-2026)/(2031-2026)),IF(A7<=2036,3.46*(3.9/3.46)^((A7-2031)/(2036-2031)),IF(A7<=2041,3.9*(4.34/3.9)^((A7-2036)/(2041-2036)),4.34*(4.84/4.34)^((A7-2041)/(2046-2041))))))) -> 3.2267169 | F7: =(D7/E7)/($D$4/$E$4) -> 0.975662 | G7: FAA Table A-2 baseline; annual values geometrically interpolated between published anchor years | H7: 2036: ASM 1,816.5; yield 19.73; CPI 3.90
A8: 2029 | B8: =IF(A8=2025,1375,IF(A8<=2026,1375*(1405.3/1375)^((A8-2025)/(2026-2025)),IF(A8<=2031,1405.3*(1581/1405.3)^((A8-2026)/(2031-2026)),IF(A8<=2036,1581*(1816.5/1581)^((A8-2031)/(2036-2031)),IF(A8<=2041,1816.5*(2057.2/1816.5)^((A8-2036)/(2041-2036)),2057.2*(2315/2057.2)^((A8-2041)/(2046-2041))))))) -> 1508.2271 | C8: =B8/$B$4 -> 1.0968924 | D8: =IF(A8=2025,16.19,IF(A8<=2026,16.19*(16.36/16.19)^((A8-2025)/(2026-2025)),IF(A8<=2031,16.36*(17.98/16.36)^((A8-2026)/(2031-2026)),IF(A8<=2036,17.98*(19.73/17.98)^((A8-2031)/(2036-2031)),IF(A8<=2041,19.73*(21.27/19.73)^((A8-2036)/(2041-2036)),21.27*(22.97/21.27)^((A8-2041)/(2046-2041))))))) -> 17.31359 | E8: =IF(A8=2025,3,IF(A8<=2026,3*(3.08/3)^((A8-2025)/(2026-2025)),IF(A8<=2031,3.08*(3.46/3.08)^((A8-2026)/(2031-2026)),IF(A8<=2036,3.46*(3.9/3.46)^((A8-2031)/(2036-2031)),IF(A8<=2041,3.9*(4.34/3.9)^((A8-2036)/(2041-2036)),4.34*(4.84/4.34)^((A8-2041)/(2046-2041))))))) -> 3.3026758 | F8: =(D8/E8)/($D$4/$E$4) -> 0.97139439 | G8: FAA Table A-2 baseline; annual values geometrically interpolated between published anchor years | H8: 2041: ASM 2,057.2; yield 21.27; CPI 4.34
A9: 2030 | B9: =IF(A9=2025,1375,IF(A9<=2026,1375*(1405.3/1375)^((A9-2025)/(2026-2025)),IF(A9<=2031,1405.3*(1581/1405.3)^((A9-2026)/(2031-2026)),IF(A9<=2036,1581*(1816.5/1581)^((A9-2031)/(2036-2031)),IF(A9<=2041,1816.5*(2057.2/1816.5)^((A9-2036)/(2041-2036)),2057.2*(2315/2057.2)^((A9-2041)/(2046-2041))))))) -> 1544.1849 | C9: =B9/$B$4 -> 1.1230436 | D9: =IF(A9=2025,16.19,IF(A9<=2026,16.19*(16.36/16.19)^((A9-2025)/(2026-2025)),IF(A9<=2031,16.36*(17.98/16.36)^((A9-2026)/(2031-2026)),IF(A9<=2036,17.98*(19.73/17.98)^((A9-2031)/(2036-2031)),IF(A9<=2041,19.73*(21.27/19.73)^((A9-2036)/(2041-2036)),21.27*(22.97/21.27)^((A9-2041)/(2046-2041))))))) -> 17.643649 | E9: =IF(A9=2025,3,IF(A9<=2026,3*(3.08/3)^((A9-2025)/(2026-2025)),IF(A9<=2031,3.08*(3.46/3.08)^((A9-2026)/(2031-2026)),IF(A9<=2036,3.46*(3.9/3.46)^((A9-2031)/(2036-2031)),IF(A9<=2041,3.9*(4.34/3.9)^((A9-2036)/(2041-2036)),4.34*(4.84/4.34)^((A9-2041)/(2046-2041))))))) -> 3.3804228 | F9: =(D9/E9)/($D$4/$E$4) -> 0.96714545 | G9: FAA Table A-2 baseline; annual values geometrically interpolated between published anchor years | H9: 2046: ASM 2,315.0; yield 22.97; CPI 4.84
A10: 2031 | B10: =IF(A10=2025,1375,IF(A10<=2026,1375*(1405.3/1375)^((A10-2025)/(2026-2025)),IF(A10<=2031,1405.3*(1581/1405.3)^((A10-2026)/(2031-2026)),IF(A10<=2036,1581*(1816.5/1581)^((A10-2031)/(2036-2031)),IF(A10<=2041,1816.5*(2057.2/1816.5)^((A10-2036)/(2041-2036)),2057.2*(2315/2057.2)^((A10-2041)/(2046-2041))))))) -> 1581 | C10: =B10/$B$4 -> 1.1498182 | D10: =IF(A10=2025,16.19,IF(A10<=2026,16.19*(16.36/16.19)^((A10-2025)/(2026-2025)),IF(A10<=2031,16.36*(17.98/16.36)^((A10-2026)/(2031-2026)),IF(A10<=2036,17.98*(19.73/17.98)^((A10-2031)/(2036-2031)),IF(A10<=2041,19.73*(21.27/19.73)^((A10-2036)/(2041-2036)),21.27*(22.97/21.27)^((A10-2041)/(2046-2041))))))) -> 17.98 | E10: =IF(A10=2025,3,IF(A10<=2026,3*(3.08/3)^((A10-2025)/(2026-2025)),IF(A10<=2031,3.08*(3.46/3.08)^((A10-2026)/(2031-2026)),IF(A10<=2036,3.46*(3.9/3.46)^((A10-2031)/(2036-2031)),IF(A10<=2041,3.9*(4.34/3.9)^((A10-2036)/(2041-2036)),4.34*(4.84/4.34)^((A10-2041)/(2046-2041))))))) -> 3.46 | F10: =(D10/E10)/($D$4/$E$4) -> 0.96291509 | G10: FAA Table A-2 baseline; annual values geometrically interpolated between published anchor years
A11: 2032 | B11: =IF(A11=2025,1375,IF(A11<=2026,1375*(1405.3/1375)^((A11-2025)/(2026-2025)),IF(A11<=2031,1405.3*(1581/1405.3)^((A11-2026)/(2031-2026)),IF(A11<=2036,1581*(1816.5/1581)^((A11-2031)/(2036-2031)),IF(A11<=2041,1816.5*(2057.2/1816.5)^((A11-2036)/(2041-2036)),2057.2*(2315/2057.2)^((A11-2041)/(2046-2041))))))) -> 1625.521 | C11: =B11/$B$4 -> 1.1821971 | D11: =IF(A11=2025,16.19,IF(A11<=2026,16.19*(16.36/16.19)^((A11-2025)/(2026-2025)),IF(A11<=2031,16.36*(17.98/16.36)^((A11-2026)/(2031-2026)),IF(A11<=2036,17.98*(19.73/17.98)^((A11-2031)/(2036-2031)),IF(A11<=2041,19.73*(21.27/19.73)^((A11-2036)/(2041-2036)),21.27*(22.97/21.27)^((A11-2041)/(2046-2041))))))) -> 18.317119 | E11: =IF(A11=2025,3,IF(A11<=2026,3*(3.08/3)^((A11-2025)/(2026-2025)),IF(A11<=2031,3.08*(3.46/3.08)^((A11-2026)/(2031-2026)),IF(A11<=2036,3.46*(3.9/3.46)^((A11-2031)/(2036-2031)),IF(A11<=2041,3.9*(4.34/3.9)^((A11-2036)/(2041-2036)),4.34*(4.84/4.34)^((A11-2041)/(2046-2041))))))) -> 3.5438375 | F11: =(D11/E11)/($D$4/$E$4) -> 0.95776238 | G11: FAA Table A-2 baseline; annual values geometrically interpolated between published anchor years
A12: 2033 | B12: =IF(A12=2025,1375,IF(A12<=2026,1375*(1405.3/1375)^((A12-2025)/(2026-2025)),IF(A12<=2031,1405.3*(1581/1405.3)^((A12-2026)/(2031-2026)),IF(A12<=2036,1581*(1816.5/1581)^((A12-2031)/(2036-2031)),IF(A12<=2041,1816.5*(2057.2/1816.5)^((A12-2036)/(2041-2036)),2057.2*(2315/2057.2)^((A12-2041)/(2046-2041))))))) -> 1671.2957 | C12: =B12/$B$4 -> 1.2154877 | D12: =IF(A12=2025,16.19,IF(A12<=2026,16.19*(16.36/16.19)^((A12-2025)/(2026-2025)),IF(A12<=2031,16.36*(17.98/16.36)^((A12-2026)/(2031-2026)),IF(A12<=2036,17.98*(19.73/17.98)^((A12-2031)/(2036-2031)),IF(A12<=2041,19.73*(21.27/19.73)^((A12-2036)/(2041-2036)),21.27*(22.97/21.27)^((A12-2041)/(2046-2041))))))) -> 18.660559 | E12: =IF(A12=2025,3,IF(A12<=2026,3*(3.08/3)^((A12-2025)/(2026-2025)),IF(A12<=2031,3.08*(3.46/3.08)^((A12-2026)/(2031-2026)),IF(A12<=2036,3.46*(3.9/3.46)^((A12-2031)/(2036-2031)),IF(A12<=2041,3.9*(4.34/3.9)^((A12-2036)/(2041-2036)),4.34*(4.84/4.34)^((A12-2041)/(2046-2041))))))) -> 3.6297064 | F12: =(D12/E12)/($D$4/$E$4) -> 0.95263723 | G12: FAA Table A-2 baseline; annual values geometrically interpolated between published anchor years
A13: 2034 | B13: =IF(A13=2025,1375,IF(A13<=2026,1375*(1405.3/1375)^((A13-2025)/(2026-2025)),IF(A13<=2031,1405.3*(1581/1405.3)^((A13-2026)/(2031-2026)),IF(A13<=2036,1581*(1816.5/1581)^((A13-2031)/(2036-2031)),IF(A13<=2041,1816.5*(2057.2/1816.5)^((A13-2036)/(2041-2036)),2057.2*(2315/2057.2)^((A13-2041)/(2046-2041))))))) -> 1718.3593 | C13: =B13/$B$4 -> 1.2497159 | D13: =IF(A13=2025,16.19,IF(A13<=2026,16.19*(16.36/16.19)^((A13-2025)/(2026-2025)),IF(A13<=2031,16.36*(17.98/16.36)^((A13-2026)/(2031-2026)),IF(A13<=2036,17.98*(19.73/17.98)^((A13-2031)/(2036-2031)),IF(A13<=2041,19.73*(21.27/19.73)^((A13-2036)/(2041-2036)),21.27*(22.97/21.27)^((A13-2041)/(2046-2041))))))) -> 19.010438 | E13: =IF(A13=2025,3,IF(A13<=2026,3*(3.08/3)^((A13-2025)/(2026-2025)),IF(A13<=2031,3.08*(3.46/3.08)^((A13-2026)/(2031-2026)),IF(A13<=2036,3.46*(3.9/3.46)^((A13-2031)/(2036-2031)),IF(A13<=2041,3.9*(4.34/3.9)^((A13-2036)/(2041-2036)),4.34*(4.84/4.34)^((A13-2041)/(2046-2041))))))) -> 3.717656 | F13: =(D13/E13)/($D$4/$E$4) -> 0.94753951 | G13: FAA Table A-2 baseline; annual values geometrically interpolated between published anchor years
A14: 2035 | B14: =IF(A14=2025,1375,IF(A14<=2026,1375*(1405.3/1375)^((A14-2025)/(2026-2025)),IF(A14<=2031,1405.3*(1581/1405.3)^((A14-2026)/(2031-2026)),IF(A14<=2036,1581*(1816.5/1581)^((A14-2031)/(2036-2031)),IF(A14<=2041,1816.5*(2057.2/1816.5)^((A14-2036)/(2041-2036)),2057.2*(2315/2057.2)^((A14-2041)/(2046-2041))))))) -> 1766.7484 | C14: =B14/$B$4 -> 1.2849079 | D14: =IF(A14=2025,16.19,IF(A14<=2026,16.19*(16.36/16.19)^((A14-2025)/(2026-2025)),IF(A14<=2031,16.36*(17.98/16.36)^((A14-2026)/(2031-2026)),IF(A14<=2036,17.98*(19.73/17.98)^((A14-2031)/(2036-2031)),IF(A14<=2041,19.73*(21.27/19.73)^((A14-2036)/(2041-2036)),21.27*(22.97/21.27)^((A14-2041)/(2046-2041))))))) -> 19.366878 | E14: =IF(A14=2025,3,IF(A14<=2026,3*(3.08/3)^((A14-2025)/(2026-2025)),IF(A14<=2031,3.08*(3.46/3.08)^((A14-2026)/(2031-2026)),IF(A14<=2036,3.46*(3.9/3.46)^((A14-2031)/(2036-2031)),IF(A14<=2041,3.9*(4.34/3.9)^((A14-2036)/(2041-2036)),4.34*(4.84/4.34)^((A14-2041)/(2046-2041))))))) -> 3.8077367 | F14: =(D14/E14)/($D$4/$E$4) -> 0.94246907 | G14: FAA Table A-2 baseline; annual values geometrically interpolated between published anchor years
A15: 2036 | B15: =IF(A15=2025,1375,IF(A15<=2026,1375*(1405.3/1375)^((A15-2025)/(2026-2025)),IF(A15<=2031,1405.3*(1581/1405.3)^((A15-2026)/(2031-2026)),IF(A15<=2036,1581*(1816.5/1581)^((A15-2031)/(2036-2031)),IF(A15<=2041,1816.5*(2057.2/1816.5)^((A15-2036)/(2041-2036)),2057.2*(2315/2057.2)^((A15-2041)/(2046-2041))))))) -> 1816.5 | C15: =B15/$B$4 -> 1.3210909 | D15: =IF(A15=2025,16.19,IF(A15<=2026,16.19*(16.36/16.19)^((A15-2025)/(2026-2025)),IF(A15<=2031,16.36*(17.98/16.36)^((A15-2026)/(2031-2026)),IF(A15<=2036,17.98*(19.73/17.98)^((A15-2031)/(2036-2031)),IF(A15<=2041,19.73*(21.27/19.73)^((A15-2036)/(2041-2036)),21.27*(22.97/21.27)^((A15-2041)/(2046-2041))))))) -> 19.73 | E15: =IF(A15=2025,3,IF(A15<=2026,3*(3.08/3)^((A15-2025)/(2026-2025)),IF(A15<=2031,3.08*(3.46/3.08)^((A15-2026)/(2031-2026)),IF(A15<=2036,3.46*(3.9/3.46)^((A15-2031)/(2036-2031)),IF(A15<=2041,3.9*(4.34/3.9)^((A15-2036)/(2041-2036)),4.34*(4.84/4.34)^((A15-2041)/(2046-2041))))))) -> 3.9 | F15: =(D15/E15)/($D$4/$E$4) -> 0.93742576 | G15: FAA Table A-2 baseline; annual values geometrically interpolated between published anchor years
A16: 2037 | B16: =IF(A16=2025,1375,IF(A16<=2026,1375*(1405.3/1375)^((A16-2025)/(2026-2025)),IF(A16<=2031,1405.3*(1581/1405.3)^((A16-2026)/(2031-2026)),IF(A16<=2036,1581*(1816.5/1581)^((A16-2031)/(2036-2031)),IF(A16<=2041,1816.5*(2057.2/1816.5)^((A16-2036)/(2041-2036)),2057.2*(2315/2057.2)^((A16-2041)/(2046-2041))))))) -> 1862.2742 | C16: =B16/$B$4 -> 1.3543812 | D16: =IF(A16=2025,16.19,IF(A16<=2026,16.19*(16.36/16.19)^((A16-2025)/(2026-2025)),IF(A16<=2031,16.36*(17.98/16.36)^((A16-2026)/(2031-2026)),IF(A16<=2036,17.98*(19.73/17.98)^((A16-2031)/(2036-2031)),IF(A16<=2041,19.73*(21.27/19.73)^((A16-2036)/(2041-2036)),21.27*(22.97/21.27)^((A16-2041)/(2046-2041))))))) -> 20.028811 | E16: =IF(A16=2025,3,IF(A16<=2026,3*(3.08/3)^((A16-2025)/(2026-2025)),IF(A16<=2031,3.08*(3.46/3.08)^((A16-2026)/(2031-2026)),IF(A16<=2036,3.46*(3.9/3.46)^((A16-2031)/(2036-2031)),IF(A16<=2041,3.9*(4.34/3.9)^((A16-2036)/(2041-2036)),4.34*(4.84/4.34)^((A16-2041)/(2046-2041))))))) -> 3.984278 | F16: =(D16/E16)/($D$4/$E$4) -> 0.93149374 | G16: FAA Table A-2 baseline; annual values geometrically interpolated between published anchor years
A17: 2038 | B17: =IF(A17=2025,1375,IF(A17<=2026,1375*(1405.3/1375)^((A17-2025)/(2026-2025)),IF(A17<=2031,1405.3*(1581/1405.3)^((A17-2026)/(2031-2026)),IF(A17<=2036,1581*(1816.5/1581)^((A17-2031)/(2036-2031)),IF(A17<=2041,1816.5*(2057.2/1816.5)^((A17-2036)/(2041-2036)),2057.2*(2315/2057.2)^((A17-2041)/(2046-2041))))))) -> 1909.2019 | C17: =B17/$B$4 -> 1.3885104 | D17: =IF(A17=2025,16.19,IF(A17<=2026,16.19*(16.36/16.19)^((A17-2025)/(2026-2025)),IF(A17<=2031,16.36*(17.98/16.36)^((A17-2026)/(2031-2026)),IF(A17<=2036,17.98*(19.73/17.98)^((A17-2031)/(2036-2031)),IF(A17<=2041,19.73*(21.27/19.73)^((A17-2036)/(2041-2036)),21.27*(22.97/21.27)^((A17-2041)/(2046-2041))))))) -> 20.332147 | E17: =IF(A17=2025,3,IF(A17<=2026,3*(3.08/3)^((A17-2025)/(2026-2025)),IF(A17<=2031,3.08*(3.46/3.08)^((A17-2026)/(2031-2026)),IF(A17<=2036,3.46*(3.9/3.46)^((A17-2031)/(2036-2031)),IF(A17<=2041,3.9*(4.34/3.9)^((A17-2036)/(2041-2036)),4.34*(4.84/4.34)^((A17-2041)/(2046-2041))))))) -> 4.0703772 | F17: =(D17/E17)/($D$4/$E$4) -> 0.92559926 | G17: FAA Table A-2 baseline; annual values geometrically interpolated between published anchor years
A18: 2039 | B18: =IF(A18=2025,1375,IF(A18<=2026,1375*(1405.3/1375)^((A18-2025)/(2026-2025)),IF(A18<=2031,1405.3*(1581/1405.3)^((A18-2026)/(2031-2026)),IF(A18<=2036,1581*(1816.5/1581)^((A18-2031)/(2036-2031)),IF(A18<=2041,1816.5*(2057.2/1816.5)^((A18-2036)/(2041-2036)),2057.2*(2315/2057.2)^((A18-2041)/(2046-2041))))))) -> 1957.3121 | C18: =B18/$B$4 -> 1.4234997 | D18: =IF(A18=2025,16.19,IF(A18<=2026,16.19*(16.36/16.19)^((A18-2025)/(2026-2025)),IF(A18<=2031,16.36*(17.98/16.36)^((A18-2026)/(2031-2026)),IF(A18<=2036,17.98*(19.73/17.98)^((A18-2031)/(2036-2031)),IF(A18<=2041,19.73*(21.27/19.73)^((A18-2036)/(2041-2036)),21.27*(22.97/21.27)^((A18-2041)/(2046-2041))))))) -> 20.640078 | E18: =IF(A18=2025,3,IF(A18<=2026,3*(3.08/3)^((A18-2025)/(2026-2025)),IF(A18<=2031,3.08*(3.46/3.08)^((A18-2026)/(2031-2026)),IF(A18<=2036,3.46*(3.9/3.46)^((A18-2031)/(2036-2031)),IF(A18<=2041,3.9*(4.34/3.9)^((A18-2036)/(2041-2036)),4.34*(4.84/4.34)^((A18-2041)/(2046-2041))))))) -> 4.158337 | F18: =(D18/E18)/($D$4/$E$4) -> 0.91974207 | G18: FAA Table A-2 baseline; annual values geometrically interpolated between published anchor years
A19: 2040 | B19: =IF(A19=2025,1375,IF(A19<=2026,1375*(1405.3/1375)^((A19-2025)/(2026-2025)),IF(A19<=2031,1405.3*(1581/1405.3)^((A19-2026)/(2031-2026)),IF(A19<=2036,1581*(1816.5/1581)^((A19-2031)/(2036-2031)),IF(A19<=2041,1816.5*(2057.2/1816.5)^((A19-2036)/(2041-2036)),2057.2*(2315/2057.2)^((A19-2041)/(2046-2041))))))) -> 2006.6346 | C19: =B19/$B$4 -> 1.4593706 | D19: =IF(A19=2025,16.19,IF(A19<=2026,16.19*(16.36/16.19)^((A19-2025)/(2026-2025)),IF(A19<=2031,16.36*(17.98/16.36)^((A19-2026)/(2031-2026)),IF(A19<=2036,17.98*(19.73/17.98)^((A19-2031)/(2036-2031)),IF(A19<=2041,19.73*(21.27/19.73)^((A19-2036)/(2041-2036)),21.27*(22.97/21.27)^((A19-2041)/(2046-2041))))))) -> 20.952672 | E19: =IF(A19=2025,3,IF(A19<=2026,3*(3.08/3)^((A19-2025)/(2026-2025)),IF(A19<=2031,3.08*(3.46/3.08)^((A19-2026)/(2031-2026)),IF(A19<=2036,3.46*(3.9/3.46)^((A19-2031)/(2036-2031)),IF(A19<=2041,3.9*(4.34/3.9)^((A19-2036)/(2041-2036)),4.34*(4.84/4.34)^((A19-2041)/(2046-2041))))))) -> 4.2481976 | F19: =(D19/E19)/($D$4/$E$4) -> 0.91392195 | G19: FAA Table A-2 baseline; annual values geometrically interpolated between published anchor years

Sheet Carbon Markets
A1: Carbon Market Assumptions — Context, Not a Dynamic Pricing Engine
A3: Market / Instrument | B3: Reference Price | C3: Units | D3: Availability / Volume | E3: Timeframe | F3: How we use it | G3: Status | H3: Source URL | J3: Illustrative CORSIA Share | K3: CORSIA Price | L3: Removal Price | M3: Implied Weighted Price
A4: Broad voluntary carbon credits | B4: 3.5 | C4: $/tCO2e | D4: 202000000 | E4: 2025 retirements | F4: Context only; not used in active model | G4: Unused / context | H4: https://www.msci.com/research-and-insights/blog-post/carbon-credits-come-of-age-in-2025 | J4: 0 | K4: =Inputs!$B$32 -> 59 | L4: =Inputs!$B$33 -> 200 | M4: =J4*K4+(1-J4)*L4 -> 200
A5: Higher-rated voluntary credits (BBB+) | B5: 6.8 | C5: $/tCO2e | E5: 2025 average | F5: Context only | G5: Unused / context | H5: https://www.msci.com/research-and-insights/blog-post/carbon-credits-come-of-age-in-2025 | J5: 0.1 | K5: =Inputs!$B$32 -> 59 | L5: =Inputs!$B$33 -> 200 | M5: =J5*K5+(1-J5)*L5 -> 185.9
A6: CORSIA-eligible credits | B6: 59 | C6: $/tCO2e midpoint | E6: 2033–2035 | F6: Reference for airline compliance exposure; not blended into net-zero closure cost | G6: Unused / context | H6: https://www.msci.com/research-and-insights/paper/corsia-costs-and-implications-for-the-airline-industry | J6: 0.2 | K6: =Inputs!$B$32 -> 59 | L6: =Inputs!$B$33 -> 200 | M6: =J6*K6+(1-J6)*L6 -> 171.8
A7: Durable carbon removal planning benchmark | B7: 200 | C7: $/tCO2e | E7: Planning value | F7: Reference supporting the active $200/t default | G7: Active assumption reference | H7: https://www.nasdaq.com/products/european-markets/carbon-removal-platform | J7: 0.25 | K7: =Inputs!$B$32 -> 59 | L7: =Inputs!$B$33 -> 200 | M7: =J7*K7+(1-J7)*L7 -> 164.75
A8: Puro CORCX observed reference | B8: 150.4 | C8: EUR/tCO2e | D8: 1875765 | E8: Aug/Sep 2026 | F8: Observed durable-removal market reference only | G8: Unused / context | H8: https://www.nasdaq.com/products/european-markets/carbon-removal-platform | J8: 0.3 | K8: =Inputs!$B$32 -> 59 | L8: =Inputs!$B$33 -> 200 | M8: =J8*K8+(1-J8)*L8 -> 157.7
A9: Active model carbon planning price | B9: =Inputs!B14 -> 200 | C9: $/tCO2e | E9: Scenario | F9: Residual emissions × planning price × neutralization share | G9: ACTIVE | H9: Inputs!B14 | J9: 0.5 | K9: =Inputs!$B$32 -> 59 | L9: =Inputs!$B$33 -> 200 | M9: =J9*K9+(1-J9)*L9 -> 129.5
J11: Decision
J12: Active model | M12: Use a single $200/t planning price
J13: Why | M13: CORSIA and durable removals address different obligations; weighting them without a reliable coverage share would create false precision.

Sheet Data Map
A1: Data Map — Active vs. Context
A3: Category | B3: Metric | C3: Best Source | D3: Data Type | E3: Model Status | F3: Confidence | G3: Key Caveat
A4: Alaska business | B4: Total operating revenue | C4: 10-K | D4: Observed company primary | E4: ACTIVE — financial denominator | F4: Very high | G4: Revenue is not cash availability
A5: Alaska business | B5: Fuel gallons / into-plane fuel price | C5: 10-K | D5: Observed company primary | E5: ACTIVE | F5: Very high | G5: Operating vs environmental fuel boundary differs
A6: Alaska business | B6: Capex / aircraft commitments | C6: 10-K / 10-Q | D6: Observed / contractual primary | E6: ACTIVE — normalized to revenue | F6: Very high | G6: Commitments are not identical to annual capex
A7: Alaska business | B7: OCF / liquidity | C7: 10-K | D7: Observed company primary | E7: CONTEXT ONLY | F7: Very high | G7: No longer used as model denominator
A8: Alaska carbon | B8: 2019 / 2025 GHG intensity | C8: Impact Report | D8: Company sustainability primary | E8: ACTIVE | F8: High | G8: Not SEC financial reporting
A9: Alaska carbon | B9: Scope 1 / market-based Scope 2 emissions | C9: Impact Report | D9: Company sustainability primary | E9: ACTIVE | F9: High | G9: Scope 3 excluded
A10: Airline activity | B10: System ASM outlook | C10: FAA Aerospace Forecast | D10: Official forecast | E10: ACTIVE | F10: High for industry baseline | G10: Not Alaska-specific
A11: Airline pricing | B11: Yield / CPI / real yield | C11: FAA Aerospace Forecast | D11: Official forecast | E11: CONTEXT ONLY | F11: High | G11: Removed from revenue projection for usability
A12: Airline efficiency | B12: Aircraft Efficiency Index | C12: EIA AEO | D12: Official forecast | E12: ACTIVE | F12: High | G12: Industry average
A13: Conventional fuel | B13: Jet-fuel price index | C13: EIA AEO + Alaska actual | D13: Official forecast + company actual | E13: ACTIVE | F13: High | G13: Index applied to Alaska 2025 delivered price
A14: SAF actuals | B14: Renewable jet gallons | C14: EPA RFS | D14: Observed regulatory primary | E14: ACTIVE | F14: Very high | G14: RFS-tracked, not every global gallon
... A22: Carbon markets | B22: CORSIA / broad VCM / Puro details | C22: MSCI / Nasdaq / Puro | D22: Observed / forecast context | E22: CONTEXT ONLY | F22: Mixed | G22: Different products/obligations should not be conflated

Sheet Decisions
A1: Model Decisions — Simplification & Usability
A3: Decision | B3: Chosen treatment | C3: Why | D3: Active implementation | E3: Alternative considered | F3: Status | G3: Notes
A4: Financial anchor | B4: Revenue | C4: Most intuitive denominator for other users and consistently available from Alaska filings | D4: Projected Revenue = 2025 Revenue × Business Activity Index | E4: FAA real-yield-adjusted revenue; OCF-normalized burden | F4: ACTIVE | G4: Revenue is a scale / burden denominator, not a cash-availability measure.
A5: Business activity | B5: FAA system ASM baseline + user adjustment | C5: Avoids extrapolating Alaska's short two-year history | D5: FAA annual Activity Index × (1 + user adjustment)^years | E5: Alaska 2024 PF→2025 ASM growth CAGR | F5: ACTIVE | G5: FAA remains an industry baseline, not an Alaska-specific forecast.
A6: Operational efficiency | B6: EIA aircraft-efficiency index + user adjustment | C6: Uses published annual industry efficiency series directly | D6: EIA Efficiency Index × (1 + user adjustment)^years | E6: Flat 0.8% annual improvement assumption | F6: ACTIVE | G6: Fleet-renewal lever is incremental beyond this baseline.
A7: Financial burden metrics | B7: Share of projected revenue | C7: Comparable across years and easy to communicate | D7: SAF premium / Revenue; Fleet capital / Revenue; Combined known burden / Revenue | E7: Share of OCF | F7: ACTIVE | G7: Do not interpret as solvency or free-cash-flow analysis.
A8: Catalytic Capital | B8: % of projected revenue | C8: Simple, reusable control for non-financial-model users | D8: Projected Revenue × Catalytic Capital % | E8: % of OCF / available cash | F8: ACTIVE | G8: Investment only increases future SAF capacity after lag; no automatic price discount.
A9: Carbon pricing | B9: Single planning price | C9: Avoids false precision from mixing non-equivalent carbon markets | D9: Carbon Closure Cost = Residual tCO2e × Carbon Planning Price × Neutralization % | E9: Dynamic CORSIA + durable-removal weighted price | F9: ACTIVE | G9: Default = $200/t. CORSIA and removal market references stay documented as context.
A10: CORSIA vs removals | B10: Keep separate conceptually | C10: CORSIA compliance and durable removals address different obligations | D10: No CORSIA cost in core model until covered-emissions share is explicitly modeled | E10: Blend prices without route/emissions coverage data | F10: ACTIVE | G10: A weighted-price sensitivity is documented, but not used.
A11: SAF supply | B11: Published anchors + explicit scenario | C11: Emerging market history is too nonlinear for trend fitting | D11: EPA actuals → 2030 probable production → 2035 base/conservative → explicit post-2035 growth | E11: Linear or exponential fit to EPA history | F11: ACTIVE | G11: DOE 2030 announced capacity remains an upper reference, not realized production.
A12: SAF pricing | B12: Market premium + partner coverage | C12: Separates physical market price from Alaska's net burden | D12: Net SAF Price = Jet Price × [1 + Market Premium × (1 − Partner Share)] | E12: One fixed SAF price | F12: ACTIVE | G12: Catalytic Capital does not automatically lower price.
A13: Unused / context data | B13: Document rather than delete | C13: Preserves research while keeping active logic legible | D13: See Unused Data sheet | E13: Leave all data mixed into active tabs | F13: ACTIVE | G13: Archive/context sheets can be physically separated later without changing core logic.
A16: Illustrative carbon-price blend (NOT active) | B16: CORSIA Share | C16: Formula | D16: Implied Price
A17: CORSIA midpoint $59/t + durable removal benchmark $200/t | B17: 0 | C17: 0% × $59 + 100% × $200 | D17: =B17*Inputs!$B$32+(1-B17)*Inputs!$B$33 -> 200
A18: CORSIA midpoint $59/t + durable removal benchmark $200/t | B18: 0.1 | C18: 10% × $59 + 90% × $200 | D18: =B18*Inputs!$B$32+(1-B18)*Inputs!$B$33 -> 185.9
A19: CORSIA midpoint $59/t + durable removal benchmark $200/t | B19: 0.2 | C19: 20% × $59 + 80% × $200 | D19: =B19*Inputs!$B$32+(1-B19)*Inputs!$B$33 -> 171.8
A20: CORSIA midpoint $59/t + durable removal benchmark $200/t | B20: 0.25 | C20: 25% × $59 + 75% × $200 | D20: =B20*Inputs!$B$32+(1-B20)*Inputs!$B$33 -> 164.75
A21: CORSIA midpoint $59/t + durable removal benchmark $200/t | B21: 0.3 | C21: 30% × $59 + 70% × $200 | D21: =B21*Inputs!$B$32+(1-B21)*Inputs!$B$33 -> 157.7
A22: CORSIA midpoint $59/t + durable removal benchmark $200/t | B22: 0.5 | C22: 50% × $59 + 50% × $200 | D22: =B22*Inputs!$B$32+(1-B22)*Inputs!$B$33 -> 129.5
A23: Reference: a 20% CORSIA / 80% removal blend equals $171.80/t; a 25% / 75% blend equals $164.75/t. The active model deliberately retains $200/t because a true CORSIA-covered emissions share has not been established and CORSIA credits are not a substitute for durable net-zero removals.

Sheet Unused Data
A1: Unused / Context Data — Not in the Active Model Engine
A3: Sheet / Dataset | B3: Unused or context fields | C3: Why not active | D3: Keep for | E3: Recommendation | F3: Active replacement
A4: Production | B4: All current rows (e.g., Twelve Moses Lake 50k gal datapoint) | C4: Single project datapoint is not representative of U.S. supply | D4: Research archive / case examples | E4: Move to Archive / Research group | F4: SAF Supply published national anchors
A5: Targets | B5: UK/EU blend mandates; U.S. production target rows | C5: Policy context is outside current physical/economic engine | D5: Policy discussion | E5: Archive separately | F5: SAF Supply; user target shares
A6: Alaska Report | B6: RPMs, passengers, ASMs/gal, RASM, PRASM, CASMex, adjusted pretax margin | C6: Not required for current emissions / revenue-burden calculations | D6: Operational QA / richer airline economics | E6: Keep as supporting company data | F6: Alaska Base + Model
A7: Alaska Report | B7: 2024 PF operating metrics / YoY growth row | C7: Short history no longer drives forward growth | D7: Historical calibration | E7: Keep as QA only | F7: FAA activity baseline
A8: Alaska Base | B8: Passenger Revenue | C8: Core model uses total operating revenue as common denominator | D8: Optional passenger-fare analysis | E8: Context only | F8: Total Operating Revenue
A9: Alaska Base | B9: 2024 PF ASM / 2025 ASM / observed ASM growth | C9: Forward activity now uses FAA baseline | D9: Historical validation | E9: Context only | F9: FAA Forecast Activity Index
A10: Alaska Base | B10: 2025 SAF N2O Scope 1 line | C10: Not separately modeled in residual; aircraft intensity approach captures aggregate aircraft effect | D10: Disclosure reconciliation | E10: Context only | F10: Aircraft Scope 1 / intensity model
A11: Alaska Base | B11: 2025 Scope 1 total | C11: Core residual sums modeled components rather than using reported total directly | D11: QA / reconciliation | E11: Context only | F11: Aircraft + vehicle + facility components
A12: Alaska Base | B12: Environmental-reporting SAF share | C12: Active model normalizes from operating fuel boundary | D12: Boundary QA | E12: Context only | F12: Operating SAF share
A13: Alaska Base | B13: 2025 Scope 3 total | C13: Scope 3 is outside v1 operational net-zero boundary | D13: Future expanded inventory | E13: Keep visibly excluded | F13: Scope 1 + market-based Scope 2 proxy
A14: Alaska Base | B14: Cash, marketable securities, cash + securities, available liquidity, OCF | C14: Financial normalization now uses revenue; model is not a liquidity / solvency forecast | D14: Financial-health context | E14: Keep in company-data archive | F14: Projected Revenue
... A25: SAF Supply | B25: Notes / source URLs | C25: Documentation only | D25: Auditability | E25: Keep | F25: N/A

Sheet App Spec
A1: Streamlit Port — Custom Alaska Decarbonization Model
A3: Layer | B3: Component | C3: Purpose | D3: Source of Truth | E3: User Editable? | F3: Proposed App Surface | G3: Validation | H3: Notes
A4: Data | B4: Alaska company actuals | C4: Revenue, fuel, emissions, capex, commitments | D4: 10-K / 10-Q / Impact Report | E4: No | F4: Hidden data layer | G4: Regression tests vs workbook | H4: Keep raw source and normalized annual table
A5: Data | B5: FAA activity baseline | C5: 2025–2040 system ASM activity index | D5: FAA Aerospace Forecast | E5: No | F5: Hidden data layer | G5: Compare annual indices to workbook | H5: Only activity index used in core app
A6: Data | B6: EIA efficiency + jet price | C6: Aircraft efficiency index and conventional-fuel price index | D6: EIA AEO | E6: No | F6: Hidden data layer | G6: Compare annual indices to workbook | H6: Raw levels remain source audit
A7: Data | B7: EPA SAF actuals | C7: Historical renewable-jet gallons | D7: EPA RFS | E7: No | F7: Historical chart / context | G7: Annual totals reproduce workbook | H7: Do not fit CAGR
A8: Data | B8: SAF forward supply | C8: Base and conservative annual paths | D8: Published anchors + explicit scenario | E8: Partly | F8: Scenario chart | G8: Monotonic-path test | H8: Base and conservative must never decline unless user explicitly allows decline
A9: Model | B9: 2030 target engine | C9: Compute modeled intensity and 10–14% target attainment | D9: Pure Python model core | E9: Yes via scenario inputs | F9: Outcome card + target-band chart | G9: Workbook parity | H9: Primary environmental outcome #1
A10: Model | B10: 2040 physical engine | C10: Compute physical residual emissions after SAF / efficiency / fleet / propulsion | D10: Pure Python model core | E10: Yes via scenario inputs | F10: Waterfall / residual card | G10: Workbook parity | H10: Do not call physical residual 'net zero' until closure applied
A11: Model | B11: 2040 closure engine | C11: Price residual with carbon planning price | D11: Pure Python model core | E11: Yes | F11: Closure cost card | G11: Residual × price | H11: Simple single-price design
A12: Finance | B12: Revenue anchor | C12: Normalize major burdens to projected revenue | D12: 2025 revenue × FAA activity index | E12: No beyond activity adj. | F12: Cost burden bars | G12: Workbook parity | H12: User-facing financial denominator
A13: Finance | B13: Investable cash pool | C13: Budget available for decarbonization | D13: Proposed: projected revenue × investable-cash share | E13: YES — new input | F13: 2040 financial-feasibility gauge | G13: Budget identity tests | H13: Needs explicit definition before production app
A14: Outcome | B14: 2030 success | C14: Modeled reduction lands in Alaska 10–14% band | D14: Model output | E14: No | F14: Band / marker chart | G14: Green if 10–14%+, red below 10% | H14: Could distinguish within-range vs exceeds high end
... A17: Outcome | B17: Cash headroom after net zero | C17: Share of investable cash remaining after modeled decarb + closure | D17: Derived | E17: No | F17: Headline KPI | G17: >=0% feasible | H17: Proposed formula below
A20: Proposed 2040 financial-success metric | B20: Formula | C20: Interpretation | D20: Status
A21: Investable Cash Pool | B21: Projected Revenue × Investable Cash % of Revenue | C21: Annual capital pool available for decarbonization | D21: PROPOSED — not active
A22: Modeled Physical-Decarb Spend | B22: Net SAF Premium + Catalytic Capital + incremental modeled decarb capex | C22: Cash consumed before carbon closure | D22: PARTIAL — fleet/ground/propulsion incremental cost not yet modeled
A23: Cash Available for Closure | B23: MAX(0, Investable Cash Pool − Physical-Decarb Spend) | C23: Budget remaining for offsets/removals | D23: PROPOSED
A24: Carbon Closure Coverage | B24: Cash Available for Closure / Carbon Closure Cost | C24: >=1.0x means modeled closure can be funded | D24: PROPOSED
A25: Investable Cash Remaining % | B25: (Investable Cash Pool − Physical-Decarb Spend − Carbon Closure Cost) / Investable Cash Pool | C25: >=0% means net-zero closure is financially feasible inside budget | D25: PROPOSED KEY KPI
A28: Recommended repo path | B28: Role | C28: Rule | D28: Example
A29: data/raw/ | B29: Immutable source extracts | C29: No app logic here | D29: EPA / FAA / EIA / Alaska source files
A30: data/processed/ | B30: Small annual model-ready tables | C30: Deterministic rebuild from raw | D30: airline_activity.csv, saf_supply.csv
A31: config/assumptions.yaml | B31: Defaults, bounds, labels, citations | C31: No formulas hidden in UI | D31: SAF premium, carbon price, slider bounds
A32: src/model/core.py | B32: Pure deterministic model | C32: No Streamlit imports | D32: run_scenario(inputs, data) -> outputs
A33: src/model/emissions.py | B33: GHG/intensity equations | C33: Unit-tested | D33: 2030 target + 2040 residual
... A39: docs/ | B39: Decisions, sources, model boundary | C39: Version controlled | D39: model_decisions.md, sources.md
